[
  {
    "ticker": "MS",
    "name": "Morgan Stanley",
    "marketCap": 288433930240,
    "revenueGrowth": 0.191,
    "debtToEquity": 420.553,
    "trailingPE": 18.531796,
    "momentum_2m": 0.14358951824630006,
    "momentum_1w": 0.03366701604171829,
    "FundamentalFilterRating": 83,
    "price": 180.75999450683594,
    "RSI (14)": 63.94,
    "EMA (20)": 175.19,
    "MACD (12,26,9)": 3.343,
    "MACD_Signal (12,26,9)": 3.3308,
    "percent_change": 0.7,
    "TechFilterRating": 100.0,
    "news_sentiment_percent": 91.7,
    "social_sentiment_percent": null,
    "sector": "Financial Services",
    "sector_name": "XLF",
    "market_change_1d": 0.14472219768570938,
    "market_change_5d": 2.9511556036984965,
    "market_change_20d": 2.27479882758459,
    "market_trend": "up",
    "sector_change_1d": 0.4690570451050924,
    "sector_change_5d": 2.2966076284931747,
    "sector_change_20d": 6.365888247176188,
    "sector_trend": "up",
    "OverallRating": 91.6,
    "AITicker": "Morgan Stanley is a global financial services firm providing investment banking, securities, wealth management, and investment management services.",
    "AIComment": "Morgan Stanley shows a positive short-term trading outlook, supported by an upward trend in both the broader market and the financial sector. The stock's recent performance, including a positive momentum and a strong news sentiment, suggests potential for continued appreciation over the next 2-10 days. Technical indicators like RSI and MACD are favorable, indicating buying interest.",
    "AIScore": 85,
    "SL": 175.34,
    "TP": 189.8,
    "SL10": 9.7,
    "TP10": 10.5
  },
  {
    "ticker": "MRK",
    "name": "Merck & Co.",
    "marketCap": 265826598912,
    "revenueGrowth": 0.037,
    "debtToEquity": 79.708,
    "trailingPE": 14.077381,
    "momentum_2m": 0.27885881874593466,
    "momentum_1w": 0.07304902928301304,
    "FundamentalFilterRating": 83,
    "price": 106.36000061035156,
    "RSI (14)": 67.34,
    "EMA (20)": 101.16,
    "MACD (12,26,9)": 1.0564,
    "MACD_Signal (12,26,9)": 0.259,
    "percent_change": 1.26,
    "TechFilterRating": 100.0,
    "news_sentiment_percent": 75.0,
    "social_sentiment_percent": null,
    "sector": "Healthcare",
    "sector_name": "XLV",
    "market_change_1d": 0.14472219768570938,
    "market_change_5d": 2.9511556036984965,
    "market_change_20d": 2.27479882758459,
    "market_trend": "up",
    "sector_change_1d": 0.4617016615923841,
    "sector_change_5d": 1.676736371422849,
    "sector_change_20d": -1.5124751110652146,
    "sector_trend": "up",
    "OverallRating": 86.0,
    "AITicker": "Merck & Co., a leading global healthcare company, focuses on pharmaceuticals and health-related products.",
    "AIComment": "Merck & Co. (MRK) shows strong potential for short-term trading, supported by positive market and sector trends. The stock's recent performance, including a 1.26% price increase and a robust RSI of 67.34, suggests upward momentum. Additionally, positive news sentiment and favorable technical indicators like MACD above its signal line further support a bullish outlook for the next 2-10 days.",
    "AIScore": 85,
    "SL": 103.17,
    "TP": 111.68,
    "SL10": 9.7,
    "TP10": 10.5
  },
  {
    "ticker": "JPM",
    "name": "JPMorgan Chase",
    "marketCap": 902139215872,
    "revenueGrowth": 0.088,
    "debtToEquity": null,
    "trailingPE": 16.25768,
    "momentum_2m": 0.045160695088334535,
    "momentum_1w": 0.04158986325804048,
    "FundamentalFilterRating": 83,
    "price": 328.2749938964844,
    "RSI (14)": 60.54,
    "EMA (20)": 315.1,
    "MACD (12,26,9)": 5.5469,
    "MACD_Signal (12,26,9)": 4.5101,
    "percent_change": 0.72,
    "TechFilterRating": 100.0,
    "news_sentiment_percent": 75.0,
    "social_sentiment_percent": null,
    "sector": "Financial Services",
    "sector_name": "XLF",
    "market_change_1d": 0.14472219768570938,
    "market_change_5d": 2.9511556036984965,
    "market_change_20d": 2.27479882758459,
    "market_trend": "up",
    "sector_change_1d": 0.4690570451050924,
    "sector_change_5d": 2.2966076284931747,
    "sector_change_20d": 6.365888247176188,
    "sector_trend": "up",
    "OverallRating": 86.0,
    "AITicker": "JPMorgan Chase is a leading global financial services firm providing investment banking, financial services for consumers and small businesses, commercial banking, financial transaction processing, and asset management.",
    "AIComment": "JPMorgan Chase appears to be a favorable short-term trading opportunity given the positive trends in both the broader market and the financial sector. The stock's recent performance, indicated by a positive momentum and an RSI of 60.54, suggests strength. The MACD above its signal line further supports bullish sentiment in the 2-10 day window.",
    "AIScore": 82,
    "SL": 318.43,
    "TP": 341.41,
    "SL10": 9.7,
    "TP10": 10.4
  },
  {
    "ticker": "SNDK",
    "name": "Sandisk",
    "marketCap": 37728653312,
    "revenueGrowth": 0.226,
    "debtToEquity": 16.661,
    "trailingPE": null,
    "momentum_2m": 1.2944742374651153,
    "momentum_1w": 0.24469371059471068,
    "FundamentalFilterRating": 66,
    "price": 257.2349853515625,
    "RSI (14)": 65.0,
    "EMA (20)": 227.1,
    "MACD (12,26,9)": 4.8679,
    "MACD_Signal (12,26,9)": 0.4173,
    "percent_change": 5.04,
    "TechFilterRating": 100.0,
    "news_sentiment_percent": 91.7,
    "social_sentiment_percent": null,
    "sector": "Technology",
    "sector_name": "XLK",
    "market_change_1d": 0.14472219768570938,
    "market_change_5d": 2.9511556036984965,
    "market_change_20d": 2.27479882758459,
    "market_trend": "up",
    "sector_change_1d": 0.09592284520436589,
    "sector_change_5d": 4.96562524256603,
    "sector_change_20d": 4.336862937197816,
    "sector_trend": "up",
    "OverallRating": 85.9,
    "AITicker": "Sandisk is a technology company specializing in data storage solutions, including flash memory and software.",
    "AIComment": "Sandisk appears to be a favorable short-term trading opportunity given the positive trends in both the broader market and technology sector. The stock has shown strong momentum and positive news sentiment, coupled with a rising RSI and MACD above its signal, indicating potential continued upward movement. However, the absence of a Trailing PE ratio could suggest valuation concerns.",
    "AIScore": 82,
    "SL": 249.52,
    "TP": 272.67,
    "SL10": 9.7,
    "TP10": 10.6
  },
  {
    "ticker": "BMY",
    "name": "Bristol Myers Squibb",
    "marketCap": 111264079872,
    "revenueGrowth": 0.028,
    "debtToEquity": 274.414,
    "trailingPE": 18.402357,
    "momentum_2m": 0.2285185798742695,
    "momentum_1w": 0.020634912380569803,
    "FundamentalFilterRating": 66,
    "price": 54.564998626708984,
    "RSI (14)": 65.72,
    "EMA (20)": 52.33,
    "MACD (12,26,9)": 1.5427,
    "MACD_Signal (12,26,9)": 1.3693,
    "percent_change": 0.53,
    "TechFilterRating": 100.0,
    "news_sentiment_percent": 83.3,
    "social_sentiment_percent": null,
    "sector": "Healthcare",
    "sector_name": "XLV",
    "market_change_1d": 0.14472219768570938,
    "market_change_5d": 2.9511556036984965,
    "market_change_20d": 2.27479882758459,
    "market_trend": "up",
    "sector_change_1d": 0.4617016615923841,
    "sector_change_5d": 1.676736371422849,
    "sector_change_20d": -1.5124751110652146,
    "sector_trend": "up",
    "OverallRating": 83.1,
    "AITicker": "Bristol Myers Squibb is a global biopharmaceutical company focused on discovering, developing, and delivering innovative medicines for patients with serious diseases.",
    "AIComment": "Bristol Myers Squibb (BMY) shows a positive short-term trading outlook, supported by an upward trend in both the overall market and healthcare sector. The stock's recent performance, including a 0.53% price increase and positive momentum indicators such as RSI and MACD, suggests continued strength. The high news sentiment further bolsters the case for potential gains in the next 2-10 days.",
    "AIScore": 82,
    "SL": 52.93,
    "TP": 57.29,
    "SL10": 9.7,
    "TP10": 10.5
  },
  {
    "ticker": "HWM",
    "name": "Howmet Aerospace",
    "marketCap": 84991901696,
    "revenueGrowth": 0.138,
    "debtToEquity": 65.176,
    "trailingPE": 59.31461,
    "momentum_2m": 0.0767122490435419,
    "momentum_1w": 0.1044510746675853,
    "FundamentalFilterRating": 66,
    "price": 211.3699951171875,
    "RSI (14)": 66.97,
    "EMA (20)": 200.48,
    "MACD (12,26,9)": 1.9996,
    "MACD_Signal (12,26,9)": 0.0354,
    "percent_change": 0.86,
    "TechFilterRating": 100.0,
    "news_sentiment_percent": 83.3,
    "social_sentiment_percent": null,
    "sector": "Industrials",
    "sector_name": "XLI",
    "market_change_1d": 0.14472219768570938,
    "market_change_5d": 2.9511556036984965,
    "market_change_20d": 2.27479882758459,
    "market_trend": "up",
    "sector_change_1d": 0.29300684055211246,
    "sector_change_5d": 2.904492272072967,
    "sector_change_20d": 3.9950434604265395,
    "sector_trend": "up",
    "OverallRating": 83.1,
    "AITicker": "Howmet Aerospace, an industrial company, specializes in engineered products and solutions for the aerospace and transportation sectors.",
    "AIComment": "Howmet Aerospace (HWM) shows a positive short-term trading opportunity given its alignment with the upward trends in both the broader market and its specific sector. The stock's recent performance, supported by strong momentum and positive news sentiment, suggests potential for continued appreciation over the next 2-10 days. The technical indicators such as a high RSI and positive MACD divergence further support this outlook.",
    "AIScore": 82,
    "SL": 205.03,
    "TP": 219.82,
    "SL10": 9.7,
    "TP10": 10.4
  },
  {
    "ticker": "GILD",
    "name": "Gilead Sciences",
    "marketCap": 156254814208,
    "revenueGrowth": 0.03,
    "debtToEquity": 116.243,
    "trailingPE": 19.493809,
    "momentum_2m": 0.14199770865648098,
    "momentum_1w": 0.03765655629400522,
    "FundamentalFilterRating": 83,
    "price": 125.83000183105469,
    "RSI (14)": 60.95,
    "EMA (20)": 122.85,
    "MACD (12,26,9)": 0.0851,
    "MACD_Signal (12,26,9)": -0.5588,
    "percent_change": 0.51,
    "TechFilterRating": 100.0,
    "news_sentiment_percent": 83.3,
    "social_sentiment_percent": null,
    "sector": "Healthcare",
    "sector_name": "XLV",
    "market_change_1d": 0.14472219768570938,
    "market_change_5d": 2.9511556036984965,
    "market_change_20d": 2.27479882758459,
    "market_trend": "up",
    "sector_change_1d": 0.4617016615923841,
    "sector_change_5d": 1.676736371422849,
    "sector_change_20d": -1.5124751110652146,
    "sector_trend": "up",
    "OverallRating": 88.8,
    "AITicker": "Gilead Sciences, a biopharmaceutical company, focuses on the discovery, development, and commercialization of medicines in areas of unmet medical need.",
    "AIComment": "Gilead Sciences shows a positive short-term trading outlook, supported by an upward trend in both the broader market and healthcare sector. The stock's recent performance, including a positive momentum and an RSI indicating neither overbought nor oversold conditions, suggests stability. The positive MACD divergence and strong news sentiment further bolster the case for potential gains in the 2-10 day window.",
    "AIScore": 78,
    "SL": 122.06,
    "TP": 132.12,
    "SL10": 9.7,
    "TP10": 10.5
  },
  {
    "ticker": "PFG",
    "name": "Principal Financial Group",
    "marketCap": 20075892736,
    "revenueGrowth": 0.222,
    "debtToEquity": 34.137,
    "trailingPE": 13.214076,
    "momentum_2m": 0.09724184920808532,
    "momentum_1w": 0.008392077620571481,
    "FundamentalFilterRating": 83,
    "price": 90.04000091552734,
    "RSI (14)": 67.2,
    "EMA (20)": 88.17,
    "MACD (12,26,9)": 1.4067,
    "MACD_Signal (12,26,9)": 1.4061,
    "percent_change": 0.58,
    "TechFilterRating": 100.0,
    "news_sentiment_percent": 75.0,
    "social_sentiment_percent": null,
    "sector": "Financial Services",
    "sector_name": "XLF",
    "market_change_1d": 0.14472219768570938,
    "market_change_5d": 2.9511556036984965,
    "market_change_20d": 2.27479882758459,
    "market_trend": "up",
    "sector_change_1d": 0.4690570451050924,
    "sector_change_5d": 2.2966076284931747,
    "sector_change_20d": 6.365888247176188,
    "sector_trend": "up",
    "OverallRating": 86.0,
    "AITicker": "Principal Financial Group, a company in the Financial Services sector, provides retirement, asset management, and insurance services.",
    "AIComment": "Principal Financial Group (PFG) shows a positive short-term trading outlook, supported by an upward trend in both the broader market and the financial sector. The stock's recent performance, including a slight increase in price and positive momentum indicators such as MACD above its signal, suggests potential for continued growth. The high RSI indicates some caution, but overall market and sector dynamics favor a bullish stance for the next 2-10 days.",
    "AIScore": 78,
    "SL": 87.34,
    "TP": 93.64,
    "SL10": 9.7,
    "TP10": 10.4
  },
  {
    "ticker": "CBRE",
    "name": "CBRE Group",
    "marketCap": 49195098112,
    "revenueGrowth": 0.135,
    "debtToEquity": 104.121,
    "trailingPE": 40.81728,
    "momentum_2m": 0.04918761183096554,
    "momentum_1w": 0.03312295002629595,
    "FundamentalFilterRating": 66,
    "price": 165.30499267578125,
    "RSI (14)": 59.14,
    "EMA (20)": 160.84,
    "MACD (12,26,9)": 1.2354,
    "MACD_Signal (12,26,9)": 0.6399,
    "percent_change": 0.89,
    "TechFilterRating": 100.0,
    "news_sentiment_percent": 91.7,
    "social_sentiment_percent": null,
    "sector": "Real Estate",
    "sector_name": "XLRE",
    "market_change_1d": 0.14472219768570938,
    "market_change_5d": 2.9511556036984965,
    "market_change_20d": 2.27479882758459,
    "market_trend": "up",
    "sector_change_1d": 0.5848696081798943,
    "sector_change_5d": 0.3110579672944702,
    "sector_change_20d": -1.0494249928854393,
    "sector_trend": "neutral",
    "OverallRating": 85.9,
    "AITicker": "CBRE Group is a global real estate services company, providing a broad range of services including property management and investment management.",
    "AIComment": "CBRE shows a positive short-term trading outlook based on its recent performance and market trends. The stock has outperformed the sector with a strong price momentum and positive news sentiment. Given the upward market trend and CBRE's robust technical indicators like a rising MACD above its signal, the stock appears favorable for a 2-10 day trade.",
    "AIScore": 78,
    "SL": 160.35,
    "TP": 171.92,
    "SL10": 9.7,
    "TP10": 10.4
  },
  {
    "ticker": "AMP",
    "name": "Ameriprise Financial",
    "marketCap": 47474692096,
    "revenueGrowth": 0.073,
    "debtToEquity": 54.222,
    "trailingPE": 13.861684,
    "momentum_2m": 0.028696759142230466,
    "momentum_1w": 0.033015387119391004,
    "FundamentalFilterRating": 83,
    "price": 503.68499755859375,
    "RSI (14)": 77.26,
    "EMA (20)": 482.73,
    "MACD (12,26,9)": 11.6976,
    "MACD_Signal (12,26,9)": 10.7784,
    "percent_change": 1.06,
    "TechFilterRating": 75.0,
    "news_sentiment_percent": 91.7,
    "social_sentiment_percent": null,
    "sector": "Financial Services",
    "sector_name": "XLF",
    "market_change_1d": 0.14472219768570938,
    "market_change_5d": 2.9511556036984965,
    "market_change_20d": 2.27479882758459,
    "market_trend": "up",
    "sector_change_1d": 0.4690570451050924,
    "sector_change_5d": 2.2966076284931747,
    "sector_change_20d": 6.365888247176188,
    "sector_trend": "up",
    "OverallRating": 83.2,
    "AITicker": "Ameriprise Financial, a financial services company, provides various financial products and services including wealth management, asset management, insurance, annuities, and estate planning.",
    "AIComment": "Ameriprise Financial (AMP) shows strong short-term trading potential given its alignment with the upward trends in both the broader market and its specific financial sector. The stock's recent performance, indicated by a positive momentum and a high RSI, suggests it might be slightly overbought, which could lead to a pullback. However, the positive news sentiment and strong sector performance could support further gains.",
    "AIScore": 78,
    "SL": 488.57,
    "TP": 518.8,
    "SL10": 9.7,
    "TP10": 10.3
  },
  {
    "ticker": "AME",
    "name": "Ametek",
    "marketCap": 48114638848,
    "revenueGrowth": 0.108,
    "debtToEquity": 26.09,
    "trailingPE": 32.85962,
    "momentum_2m": 0.1098653377984451,
    "momentum_1w": 0.042171126523073754,
    "FundamentalFilterRating": 83,
    "price": 208.00999450683594,
    "RSI (14)": 65.89,
    "EMA (20)": 201.73,
    "MACD (12,26,9)": 2.7396,
    "MACD_Signal (12,26,9)": 1.9968,
    "percent_change": -0.26,
    "TechFilterRating": 75.0,
    "news_sentiment_percent": 91.7,
    "social_sentiment_percent": null,
    "sector": "Industrials",
    "sector_name": "XLI",
    "market_change_1d": 0.14472219768570938,
    "market_change_5d": 2.9511556036984965,
    "market_change_20d": 2.27479882758459,
    "market_trend": "up",
    "sector_change_1d": 0.29300684055211246,
    "sector_change_5d": 2.904492272072967,
    "sector_change_20d": 3.9950434604265395,
    "sector_trend": "up",
    "OverallRating": 83.2,
    "AITicker": "AME, also known as Ametek, is a company that operates in the industrials sector, focusing on electronic instruments and electromechanical devices.",
    "AIComment": "AME shows a positive short-term trading opportunity given its alignment with the upward trends in both the broader market and its specific sector. The stock's recent momentum and technical indicators such as a rising MACD above its signal line and a strong RSI suggest it could continue to perform well. However, a slight recent price dip and a high trailing PE ratio suggest some caution is warranted.",
    "AIScore": 78,
    "SL": 201.77,
    "TP": 218.41,
    "SL10": 9.7,
    "TP10": 10.5
  },
  {
    "ticker": "CFG",
    "name": "Citizens Financial Group",
    "marketCap": 25798983680,
    "revenueGrowth": 0.136,
    "debtToEquity": null,
    "trailingPE": 16.753502,
    "momentum_2m": 0.13526789754892765,
    "momentum_1w": 0.020474334592098797,
    "FundamentalFilterRating": 83,
    "price": 59.80500030517578,
    "RSI (14)": 79.18,
    "EMA (20)": 57.45,
    "MACD (12,26,9)": 1.5708,
    "MACD_Signal (12,26,9)": 1.3956,
    "percent_change": 0.5,
    "TechFilterRating": 75.0,
    "news_sentiment_percent": 91.7,
    "social_sentiment_percent": null,
    "sector": "Financial Services",
    "sector_name": "XLF",
    "market_change_1d": 0.14472219768570938,
    "market_change_5d": 2.9511556036984965,
    "market_change_20d": 2.27479882758459,
    "market_trend": "up",
    "sector_change_1d": 0.4690570451050924,
    "sector_change_5d": 2.2966076284931747,
    "sector_change_20d": 6.365888247176188,
    "sector_trend": "up",
    "OverallRating": 83.2,
    "AITicker": "Citizens Financial Group, a financial services provider, offers banking and financial products to individuals and businesses.",
    "AIComment": "Citizens Financial Group (CFG) shows strong short-term trading potential, supported by an upward trend in both the broader market and the financial sector. The stock's recent performance, including a positive momentum and high RSI, suggests it might be slightly overbought, but the positive news sentiment and MACD above its signal indicate continued bullish behavior. However, caution is advised due to the high RSI.",
    "AIScore": 78,
    "SL": 58.01,
    "TP": 62.2,
    "SL10": 9.7,
    "TP10": 10.4
  },
  {
    "ticker": "STLD",
    "name": "Steel Dynamics",
    "marketCap": 25700448256,
    "revenueGrowth": 0.112,
    "debtToEquity": 42.166,
    "trailingPE": 23.124502,
    "momentum_2m": 0.2521695869544187,
    "momentum_1w": 0.010709683836381378,
    "FundamentalFilterRating": 83,
    "price": 174.71499633789062,
    "RSI (14)": 62.01,
    "EMA (20)": 170.71,
    "MACD (12,26,9)": 3.1396,
    "MACD_Signal (12,26,9)": 2.6656,
    "percent_change": -1.4,
    "TechFilterRating": 100.0,
    "news_sentiment_percent": 66.7,
    "social_sentiment_percent": null,
    "sector": "Basic Materials",
    "sector_name": "XLB",
    "market_change_1d": 0.14472219768570938,
    "market_change_5d": 2.9511556036984965,
    "market_change_20d": 2.27479882758459,
    "market_trend": "up",
    "sector_change_1d": -0.14207350100324811,
    "sector_change_5d": 1.6172399017432504,
    "sector_change_20d": 4.59134566049435,
    "sector_trend": "up",
    "OverallRating": 83.2,
    "AITicker": "Steel Dynamics, a company engaged in the steel production and metals recycling sectors, primarily serving the construction, automotive, and manufacturing industries.",
    "AIComment": "Steel Dynamics (STLD) shows a positive short-term trading outlook, supported by an upward trend in both the broader market and its specific sector. The stock's recent performance, including a positive momentum and a strong MACD above its signal, suggests potential for continued growth. However, a slight recent price decline and a moderate RSI indicate some caution is warranted.",
    "AIScore": 78,
    "SL": 169.47,
    "TP": 183.45,
    "SL10": 9.7,
    "TP10": 10.5
  },
  {
    "ticker": "VRTX",
    "name": "Vertex Pharmaceuticals",
    "marketCap": 118878093312,
    "revenueGrowth": 0.11,
    "debtToEquity": 10.594,
    "trailingPE": 32.675125,
    "momentum_2m": 0.18389333653335171,
    "momentum_1w": 0.03145580840456774,
    "FundamentalFilterRating": 83,
    "price": 463.42999267578125,
    "RSI (14)": 54.62,
    "EMA (20)": 448.65,
    "MACD (12,26,9)": 7.6911,
    "MACD_Signal (12,26,9)": 6.8008,
    "percent_change": 0.92,
    "TechFilterRating": 100.0,
    "news_sentiment_percent": 66.7,
    "social_sentiment_percent": null,
    "sector": "Healthcare",
    "sector_name": "XLV",
    "market_change_1d": 0.14472219768570938,
    "market_change_5d": 2.9511556036984965,
    "market_change_20d": 2.27479882758459,
    "market_trend": "up",
    "sector_change_1d": 0.45808854114108843,
    "sector_change_5d": 1.6730795520625508,
    "sector_change_20d": -1.5160172299472197,
    "sector_trend": "up",
    "OverallRating": 83.2,
    "AITicker": "Vertex Pharmaceuticals is a biotechnology company focused on developing treatments for serious diseases.",
    "AIComment": "Vertex Pharmaceuticals shows a positive short-term trading outlook, supported by an upward trend in both the broader market and healthcare sector. The stock's recent performance, including a price above its 20-day EMA and a positive MACD above its signal line, suggests continued upward momentum. The positive news sentiment further supports the likelihood of a favorable trading environment over the next 2-10 days.",
    "AIScore": 78,
    "SL": 449.53,
    "TP": 486.6,
    "SL10": 9.7,
    "TP10": 10.5
  },
  {
    "ticker": "DD",
    "name": "DuPont",
    "marketCap": 17108856832,
    "revenueGrowth": 0.073,
    "debtToEquity": 39.673,
    "trailingPE": 23.604046,
    "momentum_2m": 0.25921785251694773,
    "momentum_1w": 0.005788192590730157,
    "FundamentalFilterRating": 83,
    "price": 40.83000183105469,
    "RSI (14)": 61.05,
    "EMA (20)": 40.41,
    "MACD (12,26,9)": 0.5769,
    "MACD_Signal (12,26,9)": 0.5937,
    "percent_change": -0.51,
    "TechFilterRating": 75.0,
    "news_sentiment_percent": 100.0,
    "social_sentiment_percent": null,
    "sector": "Basic Materials",
    "sector_name": "XLB",
    "market_change_1d": 0.14472219768570938,
    "market_change_5d": 2.9511556036984965,
    "market_change_20d": 2.27479882758459,
    "market_trend": "up",
    "sector_change_1d": -0.14207350100324811,
    "sector_change_5d": 1.6172399017432504,
    "sector_change_20d": 4.59134566049435,
    "sector_trend": "up",
    "OverallRating": 86.0,
    "AITicker": "DuPont is a global innovation leader in the basic materials sector, specializing in technology-based materials, ingredients, and solutions.",
    "AIComment": "DuPont shows a positive alignment with the upward trends in both the market and its sector, suggesting a favorable environment for the stock. The recent positive momentum and strong news sentiment further support potential short-term gains. However, the slight underperformance compared to the MACD signal and a modest weekly momentum indicate some caution is warranted.",
    "AIScore": 75,
    "SL": 39.61,
    "TP": 42.87,
    "SL10": 9.7,
    "TP10": 10.5
  },
  {
    "ticker": "EPAM",
    "name": "EPAM Systems",
    "marketCap": 11687439360,
    "revenueGrowth": 0.194,
    "debtToEquity": 4.165,
    "trailingPE": 32.03664,
    "momentum_2m": 0.3916042554608181,
    "momentum_1w": 0.026966155030878625,
    "FundamentalFilterRating": 100,
    "price": 209.7100067138672,
    "RSI (14)": 61.67,
    "EMA (20)": 203.52,
    "MACD (12,26,9)": 5.7139,
    "MACD_Signal (12,26,9)": 5.9332,
    "percent_change": 0.82,
    "TechFilterRating": 75.0,
    "news_sentiment_percent": 66.7,
    "social_sentiment_percent": null,
    "sector": "Technology",
    "sector_name": "XLK",
    "market_change_1d": 0.14472219768570938,
    "market_change_5d": 2.9511556036984965,
    "market_change_20d": 2.27479882758459,
    "market_trend": "up",
    "sector_change_1d": 0.09935202157789202,
    "sector_change_5d": 4.969221249594891,
    "sector_change_20d": 4.340437403520747,
    "sector_trend": "up",
    "OverallRating": 80.6,
    "AITicker": "EPAM Systems is a company specializing in product development, digital platform engineering, and digital and product design services.",
    "AIComment": "EPAM Systems shows potential for a short-term trade, given the positive momentum in both the technology sector and the overall market. The company's recent performance, indicated by a positive revenue growth and a reasonable debt-to-equity ratio, aligns well with the upward trends in its sector and the broader market. However, a slight decrease in MACD below its signal and a moderate RSI suggest some caution.",
    "AIScore": 75,
    "SL": 203.42,
    "TP": 222.29,
    "SL10": 9.7,
    "TP10": 10.6
  },
  {
    "ticker": "CHRW",
    "name": "C.H. Robinson",
    "marketCap": 19580645376,
    "revenueGrowth": -0.109,
    "debtToEquity": 80.904,
    "trailingPE": 33.551617,
    "momentum_2m": 0.25686040845929115,
    "momentum_1w": 0.03525914302602828,
    "FundamentalFilterRating": 66,
    "price": 165.71249389648438,
    "RSI (14)": 65.21,
    "EMA (20)": 160.33,
    "MACD (12,26,9)": 2.583,
    "MACD_Signal (12,26,9)": 1.8012,
    "percent_change": 0.68,
    "TechFilterRating": 100.0,
    "news_sentiment_percent": 91.7,
    "social_sentiment_percent": null,
    "sector": "Industrials",
    "sector_name": "XLI",
    "market_change_1d": 0.14472219768570938,
    "market_change_5d": 2.9511556036984965,
    "market_change_20d": 2.27479882758459,
    "market_trend": "up",
    "sector_change_1d": 0.29300684055211246,
    "sector_change_5d": 2.904492272072967,
    "sector_change_20d": 3.9950434604265395,
    "sector_trend": "up",
    "OverallRating": 85.9,
    "AITicker": "C.H. Robinson is a global logistics company, providing freight transportation services and logistics solutions.",
    "AIComment": "C.H. Robinson shows a positive short-term trading outlook, supported by upward trends in both the broader market and the industrials sector. The stock's recent performance, including a positive momentum and a strong news sentiment, suggests potential for continued gains. However, caution is advised due to its high trailing PE ratio and a slight revenue decline.",
    "AIScore": 72,
    "SL": 160.74,
    "TP": 174.0,
    "SL10": 9.7,
    "TP10": 10.5
  },
  {
    "ticker": "AMGN",
    "name": "Amgen",
    "marketCap": 179305971712,
    "revenueGrowth": 0.124,
    "debtToEquity": 567.491,
    "trailingPE": 25.7529,
    "momentum_2m": 0.18837685150686,
    "momentum_1w": 0.021394973703267484,
    "FundamentalFilterRating": 83,
    "price": 333.1650085449219,
    "RSI (14)": 43.04,
    "EMA (20)": 329.06,
    "MACD (12,26,9)": -1.2448,
    "MACD_Signal (12,26,9)": -2.3278,
    "percent_change": 0.51,
    "TechFilterRating": 100.0,
    "news_sentiment_percent": 66.7,
    "social_sentiment_percent": null,
    "sector": "Healthcare",
    "sector_name": "XLV",
    "market_change_1d": 0.14472219768570938,
    "market_change_5d": 2.9511556036984965,
    "market_change_20d": 2.27479882758459,
    "market_trend": "up",
    "sector_change_1d": 0.4617016615923841,
    "sector_change_5d": 1.676736371422849,
    "sector_change_20d": -1.5124751110652146,
    "sector_trend": "up",
    "OverallRating": 83.2,
    "AITicker": "Amgen is a biotechnology firm focused on developing innovative therapeutics in areas of high unmet medical need.",
    "AIComment": "Amgen shows a positive short-term trading outlook based on the upward trends in both the overall market and healthcare sector. The stock's recent performance, with a slight increase in momentum and a positive MACD crossover, suggests potential for modest gains. However, the high Debt to Equity ratio and an RSI indicating neither overbought nor oversold conditions moderate the immediate upside potential.",
    "AIScore": 68,
    "SL": 323.17,
    "TP": 349.82,
    "SL10": 9.7,
    "TP10": 10.5
  },
  {
    "ticker": "INCY",
    "name": "Incyte",
    "marketCap": 19771660288,
    "revenueGrowth": 0.2,
    "debtToEquity": 0.887,
    "trailingPE": 17.06949,
    "momentum_2m": 0.187477915146665,
    "momentum_1w": 0.03154769965894744,
    "FundamentalFilterRating": 100,
    "price": 100.7300033569336,
    "RSI (14)": 50.55,
    "EMA (20)": 100.26,
    "MACD (12,26,9)": -1.1044,
    "MACD_Signal (12,26,9)": -1.7098,
    "percent_change": -0.18,
    "TechFilterRating": 75.0,
    "news_sentiment_percent": 80.6,
    "social_sentiment_percent": null,
    "sector": "Healthcare",
    "sector_name": "XLV",
    "market_change_1d": 0.14472219768570938,
    "market_change_5d": 2.9511556036984965,
    "market_change_20d": 2.27479882758459,
    "market_trend": "up",
    "sector_change_1d": 0.4617016615923841,
    "sector_change_5d": 1.676736371422849,
    "sector_change_20d": -1.5124751110652146,
    "sector_trend": "up",
    "OverallRating": 85.2,
    "AITicker": "Incyte is a biopharmaceutical company focused on the discovery, development, and commercialization of proprietary therapeutics in oncology and other areas.",
    "AIComment": "Incyte (INCY) shows a stable market and sector alignment with both trending upwards, which is generally positive. The stock's recent performance, including a slight negative percent change and a MACD value improving towards the signal line, suggests potential for recovery. Given the positive news sentiment and moderate RSI, the stock might see short-term gains, making it a reasonable candidate for a 2-10 day trade.",
    "AIScore": 65,
    "SL": 98.25,
    "TP": 105.77,
    "SL10": 9.75,
    "TP10": 10.5
  },
  {
    "ticker": "RSG",
    "name": "Republic Services",
    "marketCap": 67095175168,
    "revenueGrowth": 0.033,
    "debtToEquity": 113.763,
    "trailingPE": 31.931648,
    "momentum_2m": -0.06095275281530432,
    "momentum_1w": 0.0007916833806536072,
    "FundamentalFilterRating": 66,
    "price": 214.52999877929688,
    "RSI (14)": 48.75,
    "EMA (20)": 213.7,
    "MACD (12,26,9)": -0.3266,
    "MACD_Signal (12,26,9)": -0.4798,
    "percent_change": 0.69,
    "TechFilterRating": 100.0,
    "news_sentiment_percent": 83.3,
    "social_sentiment_percent": null,
    "sector": "Industrials",
    "sector_name": "XLI",
    "market_change_1d": 0.14472219768570938,
    "market_change_5d": 2.9511556036984965,
    "market_change_20d": 2.27479882758459,
    "market_trend": "up",
    "sector_change_1d": 0.3057492265391204,
    "sector_change_5d": 2.9175664514363486,
    "sector_change_20d": 4.008256196052407,
    "sector_trend": "up",
    "OverallRating": 83.1,
    "AITicker": "Republic Services, Inc. is a company that provides non-hazardous solid waste collection, transfer, disposal, recycling, and energy services.",
    "AIComment": "Republic Services shows a stable outlook for short-term trading, supported by a positive market and sector trend. The company's recent performance, with a slight positive momentum over the past week and a price above its 20-day EMA, suggests resilience. However, the negative short-term momentum and a MACD below its signal line indicate potential volatility, advising cautious trading.",
    "AIScore": 65,
    "SL": 209.43,
    "TP": 223.11,
    "SL10": 9.76,
    "TP10": 10.4
  }
]