[
  {
    "ticker": "AWK",
    "name": "American Water Works",
    "marketCap": 27098044416,
    "revenueGrowth": 0.058,
    "debtToEquity": 146.987,
    "trailingPE": 24.387522,
    "momentum_2m": 0.07054284171166247,
    "momentum_1w": 0.02236059646094568,
    "FundamentalFilterRating": 83,
    "price": 138.8699951171875,
    "RSI (14)": 64.89,
    "EMA (20)": 136.5,
    "MACD (12,26,9)": 0.3009,
    "MACD_Signal (12,26,9)": 0.2155,
    "percent_change": 1.47,
    "TechFilterRating": 100.0,
    "news_sentiment_percent": 75.0,
    "social_sentiment_percent": null,
    "sector": "Utilities",
    "sector_name": "XLU",
    "market_change_1d": 0.2637808149022369,
    "market_change_5d": -2.9683953450273526,
    "market_change_20d": -7.207172241388582,
    "market_trend": "down",
    "sector_change_1d": 1.2283425562990002,
    "sector_change_5d": 3.0594077354361593,
    "sector_change_20d": -1.8943285781036656,
    "sector_trend": "up",
    "OverallRating": 86.0,
    "AITicker": "American Water Works provides water and wastewater services to residential, commercial, and industrial sectors in the United States.",
    "AIComment": "American Water Works (AWK) shows potential for short-term trading given its positive momentum and sector performance. Despite a downward market trend, the utilities sector, including AWK, is trending upwards. The company's recent price increase and positive technical indicators such as RSI and MACD suggest a favorable outlook for the next 2-10 days.",
    "AIScore": 78,
    "SL": 134.7,
    "TP": 144.42,
    "SL10": 9.7,
    "TP10": 10.4,
    "Normalize": 3.6
  },
  {
    "ticker": "ETR",
    "name": "Entergy",
    "marketCap": 50254692352,
    "revenueGrowth": 0.079,
    "debtToEquity": 181.79,
    "trailingPE": 28.373402,
    "momentum_2m": 0.20815282030702487,
    "momentum_1w": 0.09473067347966957,
    "FundamentalFilterRating": 83,
    "price": 110.92500305175781,
    "RSI (14)": 64.97,
    "EMA (20)": 105.24,
    "MACD (12,26,9)": 0.1104,
    "MACD_Signal (12,26,9)": -0.5713,
    "percent_change": 0.95,
    "TechFilterRating": 100.0,
    "news_sentiment_percent": 63.9,
    "social_sentiment_percent": null,
    "sector": "Utilities",
    "sector_name": "XLU",
    "market_change_1d": 0.2637808149022369,
    "market_change_5d": -2.9683953450273526,
    "market_change_20d": -7.207172241388582,
    "market_trend": "down",
    "sector_change_1d": 1.2283425562990002,
    "sector_change_5d": 3.0594077354361593,
    "sector_change_20d": -1.8943285781036656,
    "sector_trend": "up",
    "OverallRating": 82.3,
    "AITicker": "Entergy (ETR) is a major utility company involved in the production and distribution of electricity.",
    "AIComment": "Entergy's stock shows potential for short-term trading given its positive momentum and sector performance. The utility sector is trending up, which could support further gains in ETR's stock despite the overall market trending down. The positive MACD divergence and a strong RSI suggest that the stock might continue its upward trajectory in the next 2-10 days.",
    "AIScore": 75,
    "SL": 107.6,
    "TP": 116.47,
    "SL10": 9.7,
    "TP10": 10.5,
    "Normalize": 4.5
  },
  {
    "ticker": "WEC",
    "name": "WEC Energy Group",
    "marketCap": 37744156672,
    "revenueGrowth": 0.111,
    "debtToEquity": 159.331,
    "trailingPE": 24.092806,
    "momentum_2m": 0.10812704648732074,
    "momentum_1w": 0.034238243276975,
    "FundamentalFilterRating": 83,
    "price": 115.88639831542969,
    "RSI (14)": 54.28,
    "EMA (20)": 114.95,
    "MACD (12,26,9)": -0.5871,
    "MACD_Signal (12,26,9)": -0.5912,
    "percent_change": 1.33,
    "TechFilterRating": 100.0,
    "news_sentiment_percent": 83.3,
    "social_sentiment_percent": null,
    "sector": "Utilities",
    "sector_name": "XLU",
    "market_change_1d": 0.2637808149022369,
    "market_change_5d": -2.9683953450273526,
    "market_change_20d": -7.207172241388582,
    "market_trend": "down",
    "sector_change_1d": 1.2612431695875115,
    "sector_change_5d": 3.092903470267161,
    "sector_change_20d": -1.8624428761811362,
    "sector_trend": "up",
    "OverallRating": 88.8,
    "AITicker": "WEC Energy Group is a utility company involved in the generation and distribution of electric power and natural gas.",
    "AIComment": "WEC Energy Group shows a positive short-term trading opportunity, supported by its sector's upward trend despite the overall market's downward movement. The stock's recent performance, including a positive momentum and a price above its EMA(20), aligns with a favorable RSI and MACD close to its signal line, suggesting stability. The positive news sentiment further enhances its appeal for a 2-10 day trading window.",
    "AIScore": 72,
    "SL": 112.65,
    "TP": 121.68,
    "SL10": 9.72,
    "TP10": 10.5,
    "Normalize": 4.3
  },
  {
    "ticker": "DUK",
    "name": "Duke Energy",
    "marketCap": 102926934016,
    "revenueGrowth": 0.08,
    "debtToEquity": 171.838,
    "trailingPE": 20.993649,
    "momentum_2m": 0.13801248312157988,
    "momentum_1w": 0.03863670732242164,
    "FundamentalFilterRating": 83,
    "price": 132.3300018310547,
    "RSI (14)": 58.28,
    "EMA (20)": 130.32,
    "MACD (12,26,9)": -0.494,
    "MACD_Signal (12,26,9)": -0.5615,
    "percent_change": 1.8,
    "TechFilterRating": 100.0,
    "news_sentiment_percent": 75.0,
    "social_sentiment_percent": null,
    "sector": "Utilities",
    "sector_name": "XLU",
    "market_change_1d": 0.2637808149022369,
    "market_change_5d": -2.9683953450273526,
    "market_change_20d": -7.207172241388582,
    "market_trend": "down",
    "sector_change_1d": 1.2283425562990002,
    "sector_change_5d": 3.0594077354361593,
    "sector_change_20d": -1.8943285781036656,
    "sector_trend": "up",
    "OverallRating": 86.0,
    "AITicker": "Duke Energy, a major utility company, provides electricity and gas to customers in the United States.",
    "AIComment": "Duke Energy (DUK) shows potential for a short-term trade, given its positive momentum and sector performance. Despite a general market downturn, the utilities sector, including DUK, is trending upwards. The company's recent price increase and positive news sentiment further support a bullish outlook for the next 2-10 days.",
    "AIScore": 72,
    "SL": 128.36,
    "TP": 138.95,
    "SL10": 9.7,
    "TP10": 10.5,
    "Normalize": 3.8
  },
  {
    "ticker": "LIN",
    "name": "Linde plc",
    "marketCap": 232737390592,
    "revenueGrowth": 0.058,
    "debtToEquity": 70.63,
    "trailingPE": 34.42392,
    "momentum_2m": 0.1818569735645672,
    "momentum_1w": 0.050611877297436436,
    "FundamentalFilterRating": 83,
    "price": 502.239990234375,
    "RSI (14)": 67.08,
    "EMA (20)": 492.68,
    "MACD (12,26,9)": -2.1096,
    "MACD_Signal (12,26,9)": -3.8483,
    "percent_change": 2.26,
    "TechFilterRating": 100.0,
    "news_sentiment_percent": 75.0,
    "social_sentiment_percent": null,
    "sector": "Basic Materials",
    "sector_name": "XLB",
    "market_change_1d": 0.2637808149022369,
    "market_change_5d": -2.9683953450273526,
    "market_change_20d": -7.207172241388582,
    "market_trend": "down",
    "sector_change_1d": 1.1756302693382237,
    "sector_change_5d": 4.069403584307252,
    "sector_change_20d": -6.657154072012927,
    "sector_trend": "up",
    "OverallRating": 86.0,
    "AITicker": "Linde plc is a global industrial gases and engineering company, operating in the basic materials sector.",
    "AIComment": "Linde plc shows a positive short-term trading opportunity, with a recent price increase and positive momentum over the last week and two months. Despite a downward market trend, the sector trend is up, and Linde's technical indicators like RSI and MACD suggest strength. However, caution is advised due to the overall market downturn.",
    "AIScore": 72,
    "SL": 487.17,
    "TP": 527.35,
    "SL10": 9.7,
    "TP10": 10.5,
    "Normalize": 1.0
  },
  {
    "ticker": "CMS",
    "name": "CMS Energy",
    "marketCap": 23888218112,
    "revenueGrowth": 0.123,
    "debtToEquity": 194.861,
    "trailingPE": 21.97167,
    "momentum_2m": 0.11740881076095011,
    "momentum_1w": 0.03939955378983662,
    "FundamentalFilterRating": 83,
    "price": 77.56999969482422,
    "RSI (14)": 55.53,
    "EMA (20)": 76.75,
    "MACD (12,26,9)": -0.4088,
    "MACD_Signal (12,26,9)": -0.4476,
    "percent_change": 1.78,
    "TechFilterRating": 100.0,
    "news_sentiment_percent": 66.7,
    "social_sentiment_percent": null,
    "sector": "Utilities",
    "sector_name": "XLU",
    "market_change_1d": 0.2637808149022369,
    "market_change_5d": -2.9683953450273526,
    "market_change_20d": -7.207172241388582,
    "market_trend": "down",
    "sector_change_1d": 1.2283425562990002,
    "sector_change_5d": 3.0594077354361593,
    "sector_change_20d": -1.8943285781036656,
    "sector_trend": "up",
    "OverallRating": 83.2,
    "AITicker": "CMS Energy is an energy company primarily focused on providing electricity and natural gas to customers in Michigan, USA.",
    "AIComment": "CMS Energy shows potential for short-term trading given its positive momentum and sector performance. Despite a general market downturn, the utilities sector, including CMS, is trending upwards. The stock's recent price increase and positive news sentiment further support a bullish outlook for the next 2-10 days.",
    "AIScore": 72,
    "SL": 75.24,
    "TP": 81.45,
    "SL10": 9.7,
    "TP10": 10.5,
    "Normalize": 6.4
  },
  {
    "ticker": "MDLZ",
    "name": "Mondelez International",
    "marketCap": 76215025664,
    "revenueGrowth": 0.093,
    "debtToEquity": 84.848,
    "trailingPE": 31.251322,
    "momentum_2m": 0.09725054091739249,
    "momentum_1w": 0.038779423015975034,
    "FundamentalFilterRating": 83,
    "price": 59.029998779296875,
    "RSI (14)": 61.77,
    "EMA (20)": 57.73,
    "MACD (12,26,9)": -0.3658,
    "MACD_Signal (12,26,9)": -0.7171,
    "percent_change": 1.3,
    "TechFilterRating": 100.0,
    "news_sentiment_percent": 66.7,
    "social_sentiment_percent": null,
    "sector": "Consumer Defensive",
    "sector_name": "XLP",
    "market_change_1d": 0.2637808149022369,
    "market_change_5d": -2.9683953450273526,
    "market_change_20d": -7.207172241388582,
    "market_trend": "down",
    "sector_change_1d": 0.46466726398228797,
    "sector_change_5d": 1.207198020755751,
    "sector_change_20d": -6.862292986975971,
    "sector_trend": "up",
    "OverallRating": 83.2,
    "AITicker": "Mondelez International, a major player in the consumer defensive sector, primarily focuses on manufacturing and marketing snack food and beverage products.",
    "AIComment": "Mondelez International (MDLZ) shows potential for a short-term trade, given its positive momentum and recent performance relative to its sector. Despite a general market downturn, the consumer defensive sector, to which MDLZ belongs, is trending upwards. The stock's technical indicators such as a higher RSI and positive MACD difference suggest strength, although caution is advised due to the overall market sentiment.",
    "AIScore": 72,
    "SL": 57.26,
    "TP": 61.39,
    "SL10": 9.7,
    "TP10": 10.4,
    "Normalize": 8.5
  },
  {
    "ticker": "PEP",
    "name": "PepsiCo",
    "marketCap": 215114055680,
    "revenueGrowth": 0.056,
    "debtToEquity": 258.081,
    "trailingPE": 26.220499,
    "momentum_2m": 0.10596808410331238,
    "momentum_1w": 0.042702763491204276,
    "FundamentalFilterRating": 83,
    "price": 157.3000030517578,
    "RSI (14)": 42.24,
    "EMA (20)": 156.23,
    "MACD (12,26,9)": -2.9497,
    "MACD_Signal (12,26,9)": -3.0647,
    "percent_change": 2.78,
    "TechFilterRating": 100.0,
    "news_sentiment_percent": 83.3,
    "social_sentiment_percent": null,
    "sector": "Consumer Defensive",
    "sector_name": "XLP",
    "market_change_1d": 0.2637808149022369,
    "market_change_5d": -2.9683953450273526,
    "market_change_20d": -7.207172241388582,
    "market_trend": "down",
    "sector_change_1d": 0.46466726398228797,
    "sector_change_5d": 1.207198020755751,
    "sector_change_20d": -6.862292986975971,
    "sector_trend": "up",
    "OverallRating": 88.8,
    "AITicker": "PepsiCo is a global food and beverage leader with a product portfolio including 22 brands that generate more than $1 billion each in annual retail sales.",
    "AIComment": "PepsiCo shows a positive sector trend despite a negative market trend, suggesting resilience. The stock has a recent momentum and positive news sentiment, which could support short-term gains. However, high debt-to-equity ratio and negative MACD values indicate potential risks. Suitable for cautious short-term trading.",
    "AIScore": 65,
    "SL": 153.11,
    "TP": 165.17,
    "SL10": 9.73,
    "TP10": 10.5,
    "Normalize": 3.2
  },
  {
    "ticker": "MO",
    "name": "Altria",
    "marketCap": 112286343168,
    "revenueGrowth": -0.005,
    "debtToEquity": null,
    "trailingPE": 16.235437,
    "momentum_2m": 0.17951479346699872,
    "momentum_1w": 0.05623272233816712,
    "FundamentalFilterRating": 66,
    "price": 66.94000244140625,
    "RSI (14)": 54.77,
    "EMA (20)": 65.49,
    "MACD (12,26,9)": -0.4881,
    "MACD_Signal (12,26,9)": -0.7005,
    "percent_change": 0.69,
    "TechFilterRating": 100.0,
    "news_sentiment_percent": 91.7,
    "social_sentiment_percent": null,
    "sector": "Consumer Defensive",
    "sector_name": "XLP",
    "market_change_1d": 0.2637808149022369,
    "market_change_5d": -2.9683953450273526,
    "market_change_20d": -7.207172241388582,
    "market_trend": "down",
    "sector_change_1d": 0.46466726398228797,
    "sector_change_5d": 1.207198020755751,
    "sector_change_20d": -6.862292986975971,
    "sector_trend": "up",
    "OverallRating": 85.9,
    "AITicker": "Altria Group, Inc., known by its ticker MO, is a company in the consumer defensive sector, primarily engaged in the manufacture and sale of tobacco products and related items.",
    "AIComment": "Altria's stock (MO) shows mixed signals for a short-term trade of 2-10 days. While the overall market trend is downward, the consumer defensive sector, to which Altria belongs, is trending upwards. The positive sector trend and strong news sentiment might support the stock, but the negative market momentum and slight revenue decline could pose risks.",
    "AIScore": 65,
    "SL": 64.93,
    "TP": 70.29,
    "SL10": 9.7,
    "TP10": 10.5,
    "Normalize": 7.5
  },
  {
    "ticker": "EVRG",
    "name": "Evergy",
    "marketCap": 18828032000,
    "revenueGrowth": 0.066,
    "debtToEquity": 149.917,
    "trailingPE": 22.338799,
    "momentum_2m": 0.13738872554732162,
    "momentum_1w": 0.02959322964044131,
    "FundamentalFilterRating": 83,
    "price": 81.7699966430664,
    "RSI (14)": 49.26,
    "EMA (20)": 81.41,
    "MACD (12,26,9)": -0.6484,
    "MACD_Signal (12,26,9)": -0.6573,
    "percent_change": 1.14,
    "TechFilterRating": 100.0,
    "news_sentiment_percent": 66.7,
    "social_sentiment_percent": null,
    "sector": "Utilities",
    "sector_name": "XLU",
    "market_change_1d": 0.2637808149022369,
    "market_change_5d": -2.9683953450273526,
    "market_change_20d": -7.207172241388582,
    "market_trend": "down",
    "sector_change_1d": 1.2283425562990002,
    "sector_change_5d": 3.0594077354361593,
    "sector_change_20d": -1.8943285781036656,
    "sector_trend": "up",
    "OverallRating": 83.2,
    "AITicker": "Evergy, a utility company, focuses on providing electric power to consumers in the Midwest.",
    "AIComment": "Evergy (EVRG) shows potential for a short-term trade given its sector's positive momentum despite a general market downturn. The stock has outperformed the broader market recently, and with a positive news sentiment and stable technical indicators like a near-zero MACD difference, it could be resilient. However, its high Debt to Equity ratio and moderate RSI suggest some caution.",
    "AIScore": 65,
    "SL": 79.78,
    "TP": 85.86,
    "SL10": 9.76,
    "TP10": 10.5,
    "Normalize": 6.1
  },
  {
    "ticker": "SLB",
    "name": "Schlumberger",
    "marketCap": 79417458688,
    "revenueGrowth": 0.05,
    "debtToEquity": 45.975,
    "trailingPE": 22.512766,
    "momentum_2m": 0.38658106334427234,
    "momentum_1w": 0.0742131731836928,
    "FundamentalFilterRating": 83,
    "price": 52.845001220703125,
    "RSI (14)": 63.71,
    "EMA (20)": 49.61,
    "MACD (12,26,9)": 0.6357,
    "MACD_Signal (12,26,9)": -0.2668,
    "percent_change": -1.22,
    "TechFilterRating": 100.0,
    "news_sentiment_percent": 66.7,
    "social_sentiment_percent": null,
    "sector": "Energy",
    "sector_name": "XLE",
    "market_change_1d": 0.2637808149022369,
    "market_change_5d": -2.9683953450273526,
    "market_change_20d": -7.207172241388582,
    "market_trend": "down",
    "sector_change_1d": 0.37563425590751987,
    "sector_change_5d": 5.307726050876149,
    "sector_change_20d": 10.808695315015871,
    "sector_trend": "up",
    "OverallRating": 83.2,
    "AITicker": "Schlumberger is a leading provider of technology and services to the global energy industry.",
    "AIComment": "Schlumberger shows potential for short-term trading given its sector's positive momentum despite a general market downturn. The stock's technical indicators such as a positive MACD above its signal and a relatively high RSI suggest strength, but caution is advised due to the recent negative price change and overall market sentiment.",
    "AIScore": 65,
    "SL": 51.26,
    "TP": 56.02,
    "SL10": 9.7,
    "TP10": 10.6,
    "Normalize": 9.5
  },
  {
    "ticker": "PFE",
    "name": "Pfizer",
    "marketCap": 156116942848,
    "revenueGrowth": -0.012,
    "debtToEquity": 77.957,
    "trailingPE": 20.180147,
    "momentum_2m": 0.1206719662222453,
    "momentum_1w": 0.025214763747409163,
    "FundamentalFilterRating": 66,
    "price": 27.489999771118164,
    "RSI (14)": 53.78,
    "EMA (20)": 27.14,
    "MACD (12,26,9)": 0.0431,
    "MACD_Signal (12,26,9)": -0.0075,
    "percent_change": 1.66,
    "TechFilterRating": 100.0,
    "news_sentiment_percent": 83.3,
    "social_sentiment_percent": null,
    "sector": "Healthcare",
    "sector_name": "XLV",
    "market_change_1d": 0.2637808149022369,
    "market_change_5d": -2.9683953450273526,
    "market_change_20d": -7.207172241388582,
    "market_trend": "down",
    "sector_change_1d": 0.5130536357213833,
    "sector_change_5d": -0.5353382139955287,
    "sector_change_20d": -8.795206596458105,
    "sector_trend": "neutral",
    "OverallRating": 83.1,
    "AITicker": "Pfizer is a global pharmaceutical company specializing in the development and manufacturing of medicines and vaccines.",
    "AIComment": "Pfizer (PFE) shows a mixed short-term trading outlook. Despite a recent price increase and positive news sentiment, the overall market trend is downward, which could limit upside potential. The neutral sector trend and modest technical indicators like a positive but narrow MACD spread suggest cautious optimism. Suitable for short-term traders who can manage risk effectively.",
    "AIScore": 58,
    "SL": 26.67,
    "TP": 28.86,
    "SL10": 9.7,
    "TP10": 10.5,
    "Normalize": 18.2
  },
  {
    "ticker": "JNJ",
    "name": "Johnson & Johnson",
    "marketCap": 582894354432,
    "revenueGrowth": 0.091,
    "debtToEquity": 60.499,
    "trailingPE": 21.908968,
    "momentum_2m": 0.17497381208566698,
    "momentum_1w": 0.02741908878285848,
    "FundamentalFilterRating": 83,
    "price": 242.1649932861328,
    "RSI (14)": 46.29,
    "EMA (20)": 240.84,
    "MACD (12,26,9)": -1.8852,
    "MACD_Signal (12,26,9)": -2.3335,
    "percent_change": 0.71,
    "TechFilterRating": 100.0,
    "news_sentiment_percent": 83.3,
    "social_sentiment_percent": null,
    "sector": "Healthcare",
    "sector_name": "XLV",
    "market_change_1d": 0.2637808149022369,
    "market_change_5d": -2.9683953450273526,
    "market_change_20d": -7.207172241388582,
    "market_trend": "down",
    "sector_change_1d": 0.5130536357213833,
    "sector_change_5d": -0.5353382139955287,
    "sector_change_20d": -8.795206596458105,
    "sector_trend": "neutral",
    "OverallRating": 88.8,
    "AITicker": "Johnson & Johnson is a multinational corporation that develops medical devices, pharmaceuticals, and consumer packaged goods.",
    "AIComment": "Johnson & Johnson (JNJ) shows a mixed short-term trading outlook. The overall market is trending downwards, which could negatively impact the stock. However, the healthcare sector remains neutral, and JNJ's positive news sentiment and recent price momentum may provide some support. Caution is advised due to the negative market trend.",
    "AIScore": 55,
    "SL": 236.02,
    "TP": 254.27,
    "SL10": 9.75,
    "TP10": 10.5,
    "Normalize": 2.1
  },
  {
    "ticker": "AEP",
    "name": "American Electric Power",
    "marketCap": 71625515008,
    "revenueGrowth": 0.132,
    "debtToEquity": 154.237,
    "trailingPE": 19.78533,
    "momentum_2m": 0.1517836832985593,
    "momentum_1w": 0.030099250122116894,
    "FundamentalFilterRating": 83,
    "price": 131.85499572753906,
    "RSI (14)": 48.84,
    "EMA (20)": 130.72,
    "MACD (12,26,9)": -0.8951,
    "MACD_Signal (12,26,9)": -0.9202,
    "percent_change": 1.35,
    "TechFilterRating": 100.0,
    "news_sentiment_percent": 75.0,
    "social_sentiment_percent": null,
    "sector": "Utilities",
    "sector_name": "XLU",
    "market_change_1d": 0.2637808149022369,
    "market_change_5d": -2.9683953450273526,
    "market_change_20d": -7.207172241388582,
    "market_trend": "down",
    "sector_change_1d": 1.2283425562990002,
    "sector_change_5d": 3.0594077354361593,
    "sector_change_20d": -1.8943285781036656,
    "sector_trend": "up",
    "OverallRating": 86.0,
    "AITicker": "American Electric Power, a major utility company, provides electricity to several states in the United States.",
    "AIComment": "American Electric Power (AEP) shows a mixed short-term trading outlook. The overall market is trending down, which could negatively impact AEP. However, the utilities sector is trending up, which might provide some support. The company's recent price momentum and positive news sentiment suggest potential resilience, but the negative MACD values indicate caution.",
    "AIScore": 55,
    "SL": 128.11,
    "TP": 138.45,
    "SL10": 9.72,
    "TP10": 10.5,
    "Normalize": 3.8
  },
  {
    "ticker": "KO",
    "name": "Coca-Cola Company (The)",
    "marketCap": 330193076224,
    "revenueGrowth": 0.024,
    "debtToEquity": 139.793,
    "trailingPE": 25.235197,
    "momentum_2m": 0.10488460847049907,
    "momentum_1w": 0.02136860224333259,
    "FundamentalFilterRating": 66,
    "price": 76.74500274658203,
    "RSI (14)": 46.26,
    "EMA (20)": 76.53,
    "MACD (12,26,9)": -0.8946,
    "MACD_Signal (12,26,9)": -0.9351,
    "percent_change": 1.37,
    "TechFilterRating": 100.0,
    "news_sentiment_percent": 83.3,
    "social_sentiment_percent": null,
    "sector": "Consumer Defensive",
    "sector_name": "XLP",
    "market_change_1d": 0.2637808149022369,
    "market_change_5d": -2.9683953450273526,
    "market_change_20d": -7.207172241388582,
    "market_trend": "down",
    "sector_change_1d": 0.46466726398228797,
    "sector_change_5d": 1.207198020755751,
    "sector_change_20d": -6.862292986975971,
    "sector_trend": "up",
    "OverallRating": 83.1,
    "AITicker": "Coca-Cola Company (KO) is a global beverage leader offering over 500 brands in more than 200 countries.",
    "AIComment": "Coca-Cola (KO) shows a mixed short-term trading outlook. The overall market trend is downward, which could pressure the stock, but the consumer defensive sector is trending up, potentially offering some resilience. The stock's recent performance and positive news sentiment suggest moderate bullishness, but market conditions remain uncertain.",
    "AIScore": 55,
    "SL": 75.0,
    "TP": 80.58,
    "SL10": 9.77,
    "TP10": 10.5,
    "Normalize": 6.5
  },
  {
    "ticker": "EQT",
    "name": "EQT Corporation",
    "marketCap": 40555958272,
    "revenueGrowth": 0.269,
    "debtToEquity": 28.932,
    "trailingPE": 19.626888,
    "momentum_2m": 0.2154500806556252,
    "momentum_1w": -0.004062655302849993,
    "FundamentalFilterRating": 66,
    "price": 65.0,
    "RSI (14)": 62.28,
    "EMA (20)": 64.59,
    "MACD (12,26,9)": 1.1871,
    "MACD_Signal (12,26,9)": 0.9859,
    "percent_change": -3.77,
    "TechFilterRating": 100.0,
    "news_sentiment_percent": 75.0,
    "social_sentiment_percent": null,
    "sector": "Energy",
    "sector_name": "XLE",
    "market_change_1d": 0.2637808149022369,
    "market_change_5d": -2.9683953450273526,
    "market_change_20d": -7.207172241388582,
    "market_trend": "down",
    "sector_change_1d": 0.31968820948200527,
    "sector_change_5d": 5.249031020211747,
    "sector_change_20d": 10.74693422669597,
    "sector_trend": "up",
    "OverallRating": 80.3,
    "AITicker": "EQT Corporation is a major player in the energy sector, focusing primarily on natural gas production.",
    "AIComment": "EQT Corporation shows mixed signals for a short-term trade. The overall market is trending down, which could negatively impact the stock. However, the energy sector is trending up, which might support the stock's performance. The company's recent negative price momentum and a slight decrease in the last week are concerning, but strong news sentiment and positive sector trend could provide some buffer.",
    "AIScore": 55,
    "SL": 63.3,
    "TP": 68.25,
    "SL10": 9.74,
    "TP10": 10.5,
    "Normalize": 7.7
  },
  {
    "ticker": "MRK",
    "name": "Merck & Co.",
    "marketCap": 290728574976,
    "revenueGrowth": 0.05,
    "debtToEquity": 95.959,
    "trailingPE": 16.130316,
    "momentum_2m": 0.1254128270616235,
    "momentum_1w": 0.016511030668015847,
    "FundamentalFilterRating": 83,
    "price": 117.76000213623047,
    "RSI (14)": 56.14,
    "EMA (20)": 117.28,
    "MACD (12,26,9)": -0.2421,
    "MACD_Signal (12,26,9)": -0.799,
    "percent_change": -1.56,
    "TechFilterRating": 100.0,
    "news_sentiment_percent": 83.3,
    "social_sentiment_percent": null,
    "sector": "Healthcare",
    "sector_name": "XLV",
    "market_change_1d": 0.2637808149022369,
    "market_change_5d": -2.9683953450273526,
    "market_change_20d": -7.207172241388582,
    "market_trend": "down",
    "sector_change_1d": 0.5130536357213833,
    "sector_change_5d": -0.5353382139955287,
    "sector_change_20d": -8.795206596458105,
    "sector_trend": "neutral",
    "OverallRating": 88.8,
    "AITicker": "Merck & Co., a global healthcare company, focuses on pharmaceuticals including vaccines, biologic therapies, and animal health products.",
    "AIComment": "Merck & Co. (MRK) may face challenges in the short-term trading window of 2-10 days due to the overall market downtrend and a neutral sector trend. Despite a positive news sentiment and stable financial metrics, the negative market momentum and recent price decline could limit upside potential. The technical indicators like MACD and RSI suggest a lack of strong momentum, although the stock is not in the oversold territory.",
    "AIScore": 45,
    "SL": 114.93,
    "TP": 123.65,
    "SL10": 9.76,
    "TP10": 10.5,
    "Normalize": 4.2
  },
  {
    "ticker": "DELL",
    "name": "Dell Technologies",
    "marketCap": 111547228160,
    "revenueGrowth": 0.395,
    "debtToEquity": null,
    "trailingPE": 19.39228,
    "momentum_2m": 0.34303622437410497,
    "momentum_1w": 0.02269275589923403,
    "FundamentalFilterRating": 83,
    "price": 167.4199981689453,
    "RSI (14)": 66.53,
    "EMA (20)": 161.54,
    "MACD (12,26,9)": 5.7054,
    "MACD_Signal (12,26,9)": 3.5661,
    "percent_change": -2.56,
    "TechFilterRating": 100.0,
    "news_sentiment_percent": 66.7,
    "social_sentiment_percent": null,
    "sector": "Technology",
    "sector_name": "XLK",
    "market_change_1d": 0.2637808149022369,
    "market_change_5d": -2.9683953450273526,
    "market_change_20d": -7.207172241388582,
    "market_trend": "down",
    "sector_change_1d": -1.0467985141002223,
    "sector_change_5d": -6.126323166563696,
    "sector_change_20d": -7.7541592046980305,
    "sector_trend": "down",
    "OverallRating": 83.2,
    "AITicker": "Dell Technologies is a multinational technology company specializing in computer hardware and software, data storage, and IT services.",
    "AIComment": "Given the current downward trends in both the market and technology sector, Dell Technologies may face short-term challenges. The negative sector and market momentum, combined with a recent price decline, suggest potential volatility or further drops. However, strong fundamentals like a high RSI and positive MACD divergence could indicate underlying strength, making it a risky but potentially rewarding short-term trade.",
    "AIScore": 45,
    "SL": 162.4,
    "TP": 177.47,
    "SL10": 9.7,
    "TP10": 10.6,
    "Normalize": 3.0
  },
  {
    "ticker": "NWSA",
    "name": "News Corp (Class A)",
    "marketCap": 14287464448,
    "revenueGrowth": 0.055,
    "debtToEquity": 30.892,
    "trailingPE": 32.136364,
    "momentum_2m": -0.048682763462339684,
    "momentum_1w": 0.01999178094706533,
    "FundamentalFilterRating": 66,
    "price": 24.71500015258789,
    "RSI (14)": 61.01,
    "EMA (20)": 24.15,
    "MACD (12,26,9)": 0.1139,
    "MACD_Signal (12,26,9)": 0.0687,
    "percent_change": 1.96,
    "TechFilterRating": 100.0,
    "news_sentiment_percent": 91.7,
    "social_sentiment_percent": null,
    "sector": "Communication Services",
    "sector_name": "XLC",
    "market_change_1d": 0.2637808149022369,
    "market_change_5d": -2.9683953450273526,
    "market_change_20d": -7.207172241388582,
    "market_trend": "down",
    "sector_change_1d": 1.214494965661661,
    "sector_change_5d": -3.877209459745312,
    "sector_change_20d": -7.791874100221207,
    "sector_trend": "down",
    "OverallRating": 85.9,
    "AITicker": "News Corp (Class A), a global media and information services company involved in news and book publishing, digital real estate services, and more.",
    "AIComment": "Given the current downward trends in both the market and the Communication Services sector, caution is advised for trading News Corp in the short term (2-10 days). Despite positive news sentiment and a slight increase in price momentum, the overall negative sector and market momentum could limit upside potential.",
    "AIScore": 42,
    "SL": 23.97,
    "TP": 25.7,
    "SL10": 9.7,
    "TP10": 10.4,
    "Normalize": 20.2
  },
  {
    "ticker": "TJX",
    "name": "TJX Companies",
    "marketCap": 175165423616,
    "revenueGrowth": 0.085,
    "debtToEquity": 132.375,
    "trailingPE": 32.318275,
    "momentum_2m": 0.027504521545027583,
    "momentum_1w": 0.005686897058456486,
    "FundamentalFilterRating": 83,
    "price": 157.38999938964844,
    "RSI (14)": 45.05,
    "EMA (20)": 157.33,
    "MACD (12,26,9)": -0.6621,
    "MACD_Signal (12,26,9)": -0.8332,
    "percent_change": 1.46,
    "TechFilterRating": 100.0,
    "news_sentiment_percent": 66.7,
    "social_sentiment_percent": null,
    "sector": "Consumer Cyclical",
    "sector_name": "XLY",
    "market_change_1d": 0.2637808149022369,
    "market_change_5d": -2.9683953450273526,
    "market_change_20d": -7.207172241388582,
    "market_trend": "down",
    "sector_change_1d": 1.0266834607678632,
    "sector_change_5d": -3.0466793255122138,
    "sector_change_20d": -7.312882016632538,
    "sector_trend": "down",
    "OverallRating": 83.2,
    "AITicker": "TJX Companies is a retailer specializing in off-price apparel and home fashion products, operating stores across multiple countries.",
    "AIComment": "Given the current downward trends in both the market and the consumer cyclical sector, TJX Companies faces a challenging short-term trading environment. The negative MACD values and a RSI close to 45 suggest a lack of strong upward momentum. However, the positive news sentiment and slight recent price increase provide some counterbalance.",
    "AIScore": 42,
    "SL": 154.18,
    "TP": 163.69,
    "SL10": 9.8,
    "TP10": 10.4,
    "Normalize": 3.2
  }
]