[
  {
    "ticker": "WDC",
    "name": "Western Digital",
    "marketCap": 181533736960,
    "revenueGrowth": 0.455,
    "debtToEquity": 17.81,
    "trailingPE": 31.518253,
    "momentum_2m": 0.8841333613511884,
    "momentum_1w": 0.14838231151429815,
    "FundamentalFilterRating": 83,
    "price": 526.8200073242188,
    "RSI (14)": 63.09,
    "EMA (20)": 467.57,
    "MACD (12,26,9)": 20.1046,
    "MACD_Signal (12,26,9)": 18.6074,
    "percent_change": 8.78,
    "TechFilterRating": 100.0,
    "news_sentiment_percent": 83.3,
    "social_sentiment_percent": null,
    "sector": "Technology",
    "sector_name": "XLK",
    "market_change_1d": 0.5480715084158039,
    "market_change_5d": 1.5045200833746275,
    "market_change_20d": 4.746644606840866,
    "market_trend": "up",
    "sector_change_1d": 2.5223144670728948,
    "sector_change_5d": 6.067906511825605,
    "sector_change_20d": 15.177177558434218,
    "sector_trend": "up",
    "OverallRating": 88.8,
    "AITicker": "Western Digital is a technology company specializing in data storage solutions, including hard drives and solid state drives.",
    "AIComment": "Western Digital shows strong short-term trading potential, supported by positive market and sector trends. The stock has demonstrated significant momentum and price appreciation, with a robust news sentiment and technical indicators such as a rising MACD above its signal line. Given the upward trends in both the broader market and technology sector, the stock is likely to continue its positive trajectory over the next 2-10 days.",
    "AIScore": 88,
    "SL": 511.02,
    "TP": 558.43,
    "SL10": 9.7,
    "TP10": 10.6,
    "Normalize": 0.9
  },
  {
    "ticker": "SPG",
    "name": "Simon Property Group",
    "marketCap": 78490492928,
    "revenueGrowth": 0.193,
    "debtToEquity": 457.473,
    "trailingPE": 14.37474,
    "momentum_2m": 0.02501291729839772,
    "momentum_1w": 0.030660634310958113,
    "FundamentalFilterRating": 83,
    "price": 206.55999755859375,
    "RSI (14)": 56.76,
    "EMA (20)": 202.83,
    "MACD (12,26,9)": 0.7334,
    "MACD_Signal (12,26,9)": 0.3345,
    "percent_change": 1.05,
    "TechFilterRating": 100.0,
    "news_sentiment_percent": 100.0,
    "social_sentiment_percent": null,
    "sector": "Real Estate",
    "sector_name": "XLRE",
    "market_change_1d": 0.5480715084158039,
    "market_change_5d": 1.5045200833746275,
    "market_change_20d": 4.746644606840866,
    "market_trend": "up",
    "sector_change_1d": 0.3141817444654471,
    "sector_change_5d": 2.171430315290168,
    "sector_change_20d": 2.7822465803025276,
    "sector_trend": "up",
    "OverallRating": 94.3,
    "AITicker": "Simon Property Group, a real estate company, primarily involved in owning, developing, and managing retail real estate properties.",
    "AIComment": "Simon Property Group (SPG) shows a positive short-term trading outlook, supported by an upward trend in both the broader market and the real estate sector. The stock's recent performance, including a 1.05% price increase and positive momentum indicators such as RSI and MACD above their signal, suggests continued strength. The high news sentiment and alignment with sector growth further bolster the case for a favorable 2-10 day trading window.",
    "AIScore": 85,
    "SL": 200.36,
    "TP": 214.82,
    "SL10": 9.7,
    "TP10": 10.4,
    "Normalize": 2.4
  },
  {
    "ticker": "NXPI",
    "name": "NXP Semiconductors",
    "marketCap": 83162710016,
    "revenueGrowth": 0.122,
    "debtToEquity": 103.991,
    "trailingPE": 31.43082,
    "momentum_2m": 0.45854576962046467,
    "momentum_1w": 0.12930265114142725,
    "FundamentalFilterRating": 83,
    "price": 329.239990234375,
    "RSI (14)": 65.07,
    "EMA (20)": 292.6,
    "MACD (12,26,9)": 15.8306,
    "MACD_Signal (12,26,9)": 14.4456,
    "percent_change": 4.04,
    "TechFilterRating": 100.0,
    "news_sentiment_percent": 66.7,
    "social_sentiment_percent": null,
    "sector": "Technology",
    "sector_name": "XLK",
    "market_change_1d": 0.5480715084158039,
    "market_change_5d": 1.5045200833746275,
    "market_change_20d": 4.746644606840866,
    "market_trend": "up",
    "sector_change_1d": 2.5334039246529327,
    "sector_change_5d": 6.079379482914682,
    "sector_change_20d": 15.189635845504323,
    "sector_trend": "up",
    "OverallRating": 83.2,
    "AITicker": "NXP Semiconductors is a company specializing in high performance mixed signal solutions.",
    "AIComment": "NXP Semiconductors shows a strong short-term trading potential, supported by positive trends in both the technology sector and the broader market. The stock's recent performance, including a significant price increase and positive momentum indicators, aligns with an upward sector and market trend. The positive news sentiment further bolsters the outlook for the next 2-10 days.",
    "AIScore": 85,
    "SL": 319.36,
    "TP": 348.99,
    "SL10": 9.7,
    "TP10": 10.6,
    "Normalize": 1.5
  },
  {
    "ticker": "SNDK",
    "name": "Sandisk",
    "marketCap": 238781415424,
    "revenueGrowth": 2.51,
    "debtToEquity": 1.503,
    "trailingPE": 55.06865,
    "momentum_2m": 1.5377897119024513,
    "momentum_1w": 0.2096008449802922,
    "FundamentalFilterRating": 83,
    "price": 1612.68994140625,
    "RSI (14)": 60.51,
    "EMA (20)": 1377.36,
    "MACD (12,26,9)": 99.2102,
    "MACD_Signal (12,26,9)": 89.0156,
    "percent_change": 9.06,
    "TechFilterRating": 100.0,
    "news_sentiment_percent": 66.7,
    "social_sentiment_percent": null,
    "sector": "Technology",
    "sector_name": "XLK",
    "market_change_1d": 0.5480715084158039,
    "market_change_5d": 1.5045200833746275,
    "market_change_20d": 4.746644606840866,
    "market_trend": "up",
    "sector_change_1d": 2.5223144670728948,
    "sector_change_5d": 6.067906511825605,
    "sector_change_20d": 15.177177558434218,
    "sector_trend": "up",
    "OverallRating": 83.2,
    "AITicker": "Sandisk is a technology company specializing in data storage solutions, including flash memory and software.",
    "AIComment": "Sandisk appears to be a favorable short-term trading opportunity given the positive trends in both the broader market and the technology sector. The stock has shown strong momentum and price appreciation, supported by a robust sector performance. The technical indicators such as RSI, MACD, and EMA suggest continued strength, making it a potentially good buy for a 2-10 day trading window.",
    "AIScore": 85,
    "SL": 1564.31,
    "TP": 1709.45,
    "SL10": 9.7,
    "TP10": 10.6,
    "Normalize": 0.3
  },
  {
    "ticker": "EVRG",
    "name": "Evergy",
    "marketCap": 19448383488,
    "revenueGrowth": 0.05,
    "debtToEquity": 155.555,
    "trailingPE": 22.438831,
    "momentum_2m": 0.025509520873812086,
    "momentum_1w": 0.03802896106381737,
    "FundamentalFilterRating": 83,
    "price": 84.38999938964844,
    "RSI (14)": 63.38,
    "EMA (20)": 82.12,
    "MACD (12,26,9)": 0.5961,
    "MACD_Signal (12,26,9)": 0.3229,
    "percent_change": 0.54,
    "TechFilterRating": 100.0,
    "news_sentiment_percent": 75.0,
    "social_sentiment_percent": null,
    "sector": "Utilities",
    "sector_name": "XLU",
    "market_change_1d": 0.5480715084158039,
    "market_change_5d": 1.5045200833746275,
    "market_change_20d": 4.746644606840866,
    "market_trend": "up",
    "sector_change_1d": 0.4520437441065672,
    "sector_change_5d": 3.6754704800675997,
    "sector_change_20d": -1.3747528478297522,
    "sector_trend": "up",
    "OverallRating": 86.0,
    "AITicker": "Evergy, a utility company, focuses on providing electric power to consumers in the Midwest.",
    "AIComment": "Evergy shows a positive short-term trading outlook, supported by an upward trend in both the broader market and the utilities sector. The stock's recent performance, including a positive momentum and a strong news sentiment, aligns with these trends. The technical indicators such as RSI and MACD are favorable, suggesting continued strength over the next 2-10 days.",
    "AIScore": 82,
    "SL": 81.86,
    "TP": 87.77,
    "SL10": 9.7,
    "TP10": 10.4,
    "Normalize": 5.9
  },
  {
    "ticker": "BBY",
    "name": "Best Buy",
    "marketCap": 13164234752,
    "revenueGrowth": -0.01,
    "debtToEquity": 139.474,
    "trailingPE": 12.396826,
    "momentum_2m": 0.023581085835724824,
    "momentum_1w": 0.07947474756794937,
    "FundamentalFilterRating": 66,
    "price": 62.4900016784668,
    "RSI (14)": 68.54,
    "EMA (20)": 59.3,
    "MACD (12,26,9)": 0.5337,
    "MACD_Signal (12,26,9)": -0.0341,
    "percent_change": 1.4,
    "TechFilterRating": 100.0,
    "news_sentiment_percent": 86.1,
    "social_sentiment_percent": null,
    "sector": "Consumer Cyclical",
    "sector_name": "XLY",
    "market_change_1d": 0.5480715084158039,
    "market_change_5d": 1.5045200833746275,
    "market_change_20d": 4.746644606840866,
    "market_trend": "up",
    "sector_change_1d": -0.1678108304497994,
    "sector_change_5d": 2.2867982024485256,
    "sector_change_20d": 0.9674194284376547,
    "sector_trend": "up",
    "OverallRating": 84.0,
    "AITicker": "Best Buy Co., Inc. is a multinational retailer specializing in consumer electronics.",
    "AIComment": "Best Buy shows a positive short-term trading opportunity, supported by an upward trend in both the market and its sector. The stock's recent performance, including a strong momentum and positive news sentiment, aligns with the overall sector growth. The technical indicators such as RSI and MACD suggest a bullish momentum, making it a potentially suitable investment for a 2-10 day period.",
    "AIScore": 82,
    "SL": 60.62,
    "TP": 64.99,
    "SL10": 9.7,
    "TP10": 10.4,
    "Normalize": 8.0
  },
  {
    "ticker": "MPWR",
    "name": "Monolithic Power Systems",
    "marketCap": 81759936512,
    "revenueGrowth": 0.261,
    "debtToEquity": 0.543,
    "trailingPE": 118.953186,
    "momentum_2m": 0.45869227425589343,
    "momentum_1w": 0.11925346675410631,
    "FundamentalFilterRating": 83,
    "price": 1664.1500244140625,
    "RSI (14)": 55.31,
    "EMA (20)": 1581.85,
    "MACD (12,26,9)": -0.5472,
    "MACD_Signal (12,26,9)": -4.2667,
    "percent_change": 4.68,
    "TechFilterRating": 100.0,
    "news_sentiment_percent": 66.7,
    "social_sentiment_percent": null,
    "sector": "Technology",
    "sector_name": "XLK",
    "market_change_1d": 0.5480715084158039,
    "market_change_5d": 1.5045200833746275,
    "market_change_20d": 4.746644606840866,
    "market_trend": "up",
    "sector_change_1d": 2.5334039246529327,
    "sector_change_5d": 6.079379482914682,
    "sector_change_20d": 15.189635845504323,
    "sector_trend": "up",
    "OverallRating": 83.2,
    "AITicker": "Monolithic Power Systems, a technology company, specializes in high-performance power solutions.",
    "AIComment": "Monolithic Power Systems (MPWR) shows a promising short-term trading opportunity given the positive trends in both the broader market and technology sector. The stock's recent performance, with a significant price increase and positive momentum, aligns well with the upward sector and market trends. The technical indicators such as RSI and MACD suggest a strong position, though caution is advised due to the high trailing PE.",
    "AIScore": 82,
    "SL": 1614.23,
    "TP": 1764.0,
    "SL10": 9.7,
    "TP10": 10.6,
    "Normalize": 0.3
  },
  {
    "ticker": "RL",
    "name": "Ralph Lauren Corporation",
    "marketCap": 22905458688,
    "revenueGrowth": 0.166,
    "debtToEquity": 105.913,
    "trailingPE": 25.470549,
    "momentum_2m": 0.06430234776920529,
    "momentum_1w": 0.18102308011868762,
    "FundamentalFilterRating": 83,
    "price": 385.0,
    "RSI (14)": 58.76,
    "EMA (20)": 354.25,
    "MACD (12,26,9)": -1.0152,
    "MACD_Signal (12,26,9)": -6.0967,
    "percent_change": 1.91,
    "TechFilterRating": 100.0,
    "news_sentiment_percent": 75.0,
    "social_sentiment_percent": null,
    "sector": "Consumer Cyclical",
    "sector_name": "XLY",
    "market_change_1d": 0.5480715084158039,
    "market_change_5d": 1.5045200833746275,
    "market_change_20d": 4.746644606840866,
    "market_trend": "up",
    "sector_change_1d": -0.19298821643282116,
    "sector_change_5d": 2.261001771249993,
    "sector_change_20d": 0.9419557407052137,
    "sector_trend": "up",
    "OverallRating": 86.0,
    "AITicker": "Ralph Lauren Corporation, a major player in the fashion industry, specializes in the design and distribution of premium lifestyle products.",
    "AIComment": "Ralph Lauren Corporation shows a positive short-term trading outlook, supported by an upward trend in both the market and its sector. The stock's recent performance, including a 1.91% price increase and a strong momentum over the past week, aligns with the overall sector growth. The positive MACD signal divergence suggests potential for continued upward movement.",
    "AIScore": 78,
    "SL": 373.45,
    "TP": 400.4,
    "SL10": 9.7,
    "TP10": 10.4,
    "Normalize": 1.3
  },
  {
    "ticker": "WSM",
    "name": "Williams-Sonoma, Inc.",
    "marketCap": 23114835968,
    "revenueGrowth": 0.044,
    "debtToEquity": 79.878,
    "trailingPE": 22.032547,
    "momentum_2m": -0.04161348141547472,
    "momentum_1w": 0.16049889636273273,
    "FundamentalFilterRating": 66,
    "price": 196.30999755859375,
    "RSI (14)": 64.61,
    "EMA (20)": 182.9,
    "MACD (12,26,9)": -0.1792,
    "MACD_Signal (12,26,9)": -2.7801,
    "percent_change": 1.98,
    "TechFilterRating": 100.0,
    "news_sentiment_percent": 91.7,
    "social_sentiment_percent": null,
    "sector": "Consumer Cyclical",
    "sector_name": "XLY",
    "market_change_1d": 0.5480715084158039,
    "market_change_5d": 1.5045200833746275,
    "market_change_20d": 4.746644606840866,
    "market_trend": "up",
    "sector_change_1d": -0.19231605128453566,
    "sector_change_5d": 2.261690463158428,
    "sector_change_20d": 0.9426355493021843,
    "sector_trend": "up",
    "OverallRating": 85.9,
    "AITicker": "Williams-Sonoma, Inc. is a retailer of home furnishings and kitchenware in the consumer cyclical sector.",
    "AIComment": "Williams-Sonoma shows a positive short-term trading outlook, supported by an upward trend in both the market and its sector. The recent momentum and positive news sentiment further bolster its potential for gains. However, investors should be cautious of its slightly negative MACD values, suggesting some short-term volatility.",
    "AIScore": 78,
    "SL": 190.42,
    "TP": 204.16,
    "SL10": 9.7,
    "TP10": 10.4,
    "Normalize": 2.5
  },
  {
    "ticker": "GS",
    "name": "Goldman Sachs",
    "marketCap": 291281502208,
    "revenueGrowth": 0.145,
    "debtToEquity": 678.596,
    "trailingPE": 18.044044,
    "momentum_2m": 0.15472430178821228,
    "momentum_1w": 0.04333460043822823,
    "FundamentalFilterRating": 83,
    "price": 988.9749755859375,
    "RSI (14)": 68.54,
    "EMA (20)": 955.31,
    "MACD (12,26,9)": 13.1644,
    "MACD_Signal (12,26,9)": 6.9904,
    "percent_change": -0.78,
    "TechFilterRating": 100.0,
    "news_sentiment_percent": 66.7,
    "social_sentiment_percent": null,
    "sector": "Financial Services",
    "sector_name": "XLF",
    "market_change_1d": 0.5480715084158039,
    "market_change_5d": 1.5045200833746275,
    "market_change_20d": 4.746644606840866,
    "market_trend": "up",
    "sector_change_1d": -0.2117766626157258,
    "sector_change_5d": 0.17394694562862245,
    "sector_change_20d": 0.038603468893128046,
    "sector_trend": "neutral",
    "OverallRating": 83.2,
    "AITicker": "Goldman Sachs, a leading global investment banking, securities and investment management firm.",
    "AIComment": "Goldman Sachs (GS) shows a positive short-term trading outlook given its recent performance and market conditions. The stock's price is above its 20-day EMA and has a positive MACD indicating upward momentum. Despite a slight recent decline, the overall market trend is up and the financial sector remains stable, supporting potential gains in the next 2-10 days.",
    "AIScore": 78,
    "SL": 959.31,
    "TP": 1038.42,
    "SL10": 9.7,
    "TP10": 10.5,
    "Normalize": 0.5
  },
  {
    "ticker": "INVH",
    "name": "Invitation Homes",
    "marketCap": 17458892800,
    "revenueGrowth": 0.092,
    "debtToEquity": 97.038,
    "trailingPE": 30.936842,
    "momentum_2m": 0.12940618385717184,
    "momentum_1w": 0.022260848335597716,
    "FundamentalFilterRating": 83,
    "price": 29.395000457763672,
    "RSI (14)": 60.05,
    "EMA (20)": 28.6,
    "MACD (12,26,9)": 0.3906,
    "MACD_Signal (12,26,9)": 0.3443,
    "percent_change": 0.36,
    "TechFilterRating": 75.0,
    "news_sentiment_percent": 91.7,
    "social_sentiment_percent": null,
    "sector": "Real Estate",
    "sector_name": "XLRE",
    "market_change_1d": 0.5480715084158039,
    "market_change_5d": 1.5045200833746275,
    "market_change_20d": 4.746644606840866,
    "market_trend": "up",
    "sector_change_1d": 0.3141817444654471,
    "sector_change_5d": 2.171430315290168,
    "sector_change_20d": 2.7822465803025276,
    "sector_trend": "up",
    "OverallRating": 83.2,
    "AITicker": "Invitation Homes specializes in acquiring, renovating, leasing, and operating single-family homes as rental properties.",
    "AIComment": "Invitation Homes shows a positive short-term trading outlook, supported by an upward trend in both the broader market and the real estate sector. The company's recent performance, indicated by a rising MACD above its signal and a healthy RSI, suggests continued strength. Positive news sentiment further bolsters the potential for gains in the 2-10 day window.",
    "AIScore": 78,
    "SL": 28.51,
    "TP": 30.86,
    "SL10": 9.7,
    "TP10": 10.5,
    "Normalize": 17.0
  },
  {
    "ticker": "URI",
    "name": "United Rentals",
    "marketCap": 60375617536,
    "revenueGrowth": 0.072,
    "debtToEquity": 167.473,
    "trailingPE": 24.623148,
    "momentum_2m": 0.14969113947940005,
    "momentum_1w": 0.020305527940818635,
    "FundamentalFilterRating": 83,
    "price": 963.75,
    "RSI (14)": 57.13,
    "EMA (20)": 946.87,
    "MACD (12,26,9)": -2.3255,
    "MACD_Signal (12,26,9)": -3.1475,
    "percent_change": 2.68,
    "TechFilterRating": 100.0,
    "news_sentiment_percent": 66.7,
    "social_sentiment_percent": null,
    "sector": "Industrials",
    "sector_name": "XLI",
    "market_change_1d": 0.5480715084158039,
    "market_change_5d": 1.5045200833746275,
    "market_change_20d": 4.746644606840866,
    "market_trend": "up",
    "sector_change_1d": 1.3972136209984054,
    "sector_change_5d": 2.002927185326686,
    "sector_change_20d": 0.96226521069398,
    "sector_trend": "up",
    "OverallRating": 83.2,
    "AITicker": "United Rentals, Inc. is a company that offers equipment rental services to construction and industrial sectors.",
    "AIComment": "United Rentals shows a positive short-term trading opportunity given the upward trends in both the market and industrial sector. The stock's recent performance, including a 2.68% price increase and positive momentum indicators, aligns with the overall sector and market growth. The MACD values suggest a potential for continued upward movement, making it a suitable candidate for a 2-10 day trade.",
    "AIScore": 78,
    "SL": 934.84,
    "TP": 1011.94,
    "SL10": 9.7,
    "TP10": 10.5,
    "Normalize": 0.5
  },
  {
    "ticker": "ANET",
    "name": "Arista Networks",
    "marketCap": 200522727424,
    "revenueGrowth": 0.351,
    "debtToEquity": null,
    "trailingPE": 54.725082,
    "momentum_2m": 0.19288389513108606,
    "momentum_1w": 0.12377385121114681,
    "FundamentalFilterRating": 66,
    "price": 159.38499450683594,
    "RSI (14)": 42.79,
    "EMA (20)": 152.52,
    "MACD (12,26,9)": -4.9231,
    "MACD_Signal (12,26,9)": -6.5804,
    "percent_change": 3.48,
    "TechFilterRating": 100.0,
    "news_sentiment_percent": 83.3,
    "social_sentiment_percent": null,
    "sector": "Technology",
    "sector_name": "XLK",
    "market_change_1d": 0.5480715084158039,
    "market_change_5d": 1.5045200833746275,
    "market_change_20d": 4.746644606840866,
    "market_trend": "up",
    "sector_change_1d": 2.5112250094928568,
    "sector_change_5d": 6.056433540736528,
    "sector_change_20d": 15.164719271364113,
    "sector_trend": "up",
    "OverallRating": 83.1,
    "AITicker": "Arista Networks is a technology company specializing in high-performance cloud networking solutions.",
    "AIComment": "Arista Networks (ANET) shows potential for a short-term trade, given the positive sector and market trends. The company's sector, Technology, has outperformed with a significant 6.06% increase over the past 5 days, aligning with the overall market's upward movement. Despite a slightly bearish MACD, the positive news sentiment and recent price momentum suggest a favorable outlook for the next 2-10 days.",
    "AIScore": 78,
    "SL": 154.6,
    "TP": 167.35,
    "SL10": 9.7,
    "TP10": 10.5,
    "Normalize": 3.1
  },
  {
    "ticker": "JBL",
    "name": "Jabil",
    "marketCap": 39901093888,
    "revenueGrowth": 0.231,
    "debtToEquity": 328.91,
    "trailingPE": 50.901752,
    "momentum_2m": 0.42754616252003896,
    "momentum_1w": 0.11652348460584494,
    "FundamentalFilterRating": 66,
    "price": 378.4750061035156,
    "RSI (14)": 62.86,
    "EMA (20)": 350.9,
    "MACD (12,26,9)": 4.7768,
    "MACD_Signal (12,26,9)": 2.561,
    "percent_change": 3.88,
    "TechFilterRating": 100.0,
    "news_sentiment_percent": 83.3,
    "social_sentiment_percent": null,
    "sector": "Technology",
    "sector_name": "XLK",
    "market_change_1d": 0.5480715084158039,
    "market_change_5d": 1.5045200833746275,
    "market_change_20d": 4.746644606840866,
    "market_trend": "up",
    "sector_change_1d": 2.5334039246529327,
    "sector_change_5d": 6.079379482914682,
    "sector_change_20d": 15.189635845504323,
    "sector_trend": "up",
    "OverallRating": 83.1,
    "AITicker": "Jabil Inc., a company in the technology sector, specializes in providing comprehensive electronics design, production, and product management services.",
    "AIComment": "Jabil shows a promising short-term trading opportunity given its alignment with the upward trends in both the broader market and the technology sector. The stock's recent performance, indicated by a positive momentum and a strong news sentiment, supports potential gains. However, its high debt-to-equity ratio and trailing PE ratio suggest some caution is warranted.",
    "AIScore": 78,
    "SL": 367.12,
    "TP": 401.18,
    "SL10": 9.7,
    "TP10": 10.6,
    "Normalize": 1.3
  },
  {
    "ticker": "GEV",
    "name": "GE Vernova",
    "marketCap": 289305296896,
    "revenueGrowth": 0.163,
    "debtToEquity": 24.925,
    "trailingPE": 31.507317,
    "momentum_2m": 0.23312275960731554,
    "momentum_1w": 0.06357617235737223,
    "FundamentalFilterRating": 83,
    "price": 1077.9599609375,
    "RSI (14)": 47.38,
    "EMA (20)": 1062.87,
    "MACD (12,26,9)": -16.1221,
    "MACD_Signal (12,26,9)": -17.2275,
    "percent_change": 3.78,
    "TechFilterRating": 100.0,
    "news_sentiment_percent": 72.2,
    "social_sentiment_percent": null,
    "sector": "Industrials",
    "sector_name": "XLI",
    "market_change_1d": 0.5480715084158039,
    "market_change_5d": 1.5045200833746275,
    "market_change_20d": 4.746644606840866,
    "market_trend": "up",
    "sector_change_1d": 1.4001273327571617,
    "sector_change_5d": 2.005858302640018,
    "sector_change_20d": 0.9651664239406665,
    "sector_trend": "up",
    "OverallRating": 85.1,
    "AITicker": "GE Vernova is an industrial company involved in various sectors including energy and manufacturing.",
    "AIComment": "GE Vernova shows potential for a short-term trade, given the positive trends in both the market and its sector. The recent price momentum and positive news sentiment further support a bullish outlook. However, the negative MACD values suggest some caution is warranted.",
    "AIScore": 75,
    "SL": 1045.62,
    "TP": 1131.86,
    "SL10": 9.7,
    "TP10": 10.5,
    "Normalize": 0.5
  },
  {
    "ticker": "PNC",
    "name": "PNC Financial Services",
    "marketCap": 88547016704,
    "revenueGrowth": 0.138,
    "debtToEquity": null,
    "trailingPE": 12.81261,
    "momentum_2m": 0.04638042993436864,
    "momentum_1w": 0.031747162751990965,
    "FundamentalFilterRating": 83,
    "price": 220.39999389648438,
    "RSI (14)": 47.74,
    "EMA (20)": 217.51,
    "MACD (12,26,9)": -0.7936,
    "MACD_Signal (12,26,9)": -1.3934,
    "percent_change": 0.53,
    "TechFilterRating": 100.0,
    "news_sentiment_percent": 75.0,
    "social_sentiment_percent": null,
    "sector": "Financial Services",
    "sector_name": "XLF",
    "market_change_1d": 0.5480715084158039,
    "market_change_5d": 1.5045200833746275,
    "market_change_20d": 4.746644606840866,
    "market_trend": "up",
    "sector_change_1d": -0.2214052114171472,
    "sector_change_5d": 0.16428117842144374,
    "sector_change_20d": 0.028950760955148702,
    "sector_trend": "neutral",
    "OverallRating": 86.0,
    "AITicker": "PNC Financial Services is a major American financial services corporation providing a range of banking and financial services.",
    "AIComment": "PNC Financial Services shows a stable short-term trading opportunity, supported by a positive market trend and a neutral sector trend. The stock's recent performance, including a slight increase in price and positive momentum indicators, suggests potential for modest gains. However, the neutral sector trend and mixed technical indicators like MACD and RSI suggest cautious trading.",
    "AIScore": 65,
    "SL": 213.79,
    "TP": 229.22,
    "SL10": 9.7,
    "TP10": 10.4,
    "Normalize": 2.3
  },
  {
    "ticker": "KEY",
    "name": "KeyCorp",
    "marketCap": 23500591104,
    "revenueGrowth": 0.118,
    "debtToEquity": null,
    "trailingPE": 13.297545,
    "momentum_2m": 0.05542936384051189,
    "momentum_1w": 0.02871378979587469,
    "FundamentalFilterRating": 83,
    "price": 21.684999465942383,
    "RSI (14)": 47.07,
    "EMA (20)": 21.48,
    "MACD (12,26,9)": -0.1174,
    "MACD_Signal (12,26,9)": -0.1594,
    "percent_change": 0.58,
    "TechFilterRating": 100.0,
    "news_sentiment_percent": 66.7,
    "social_sentiment_percent": null,
    "sector": "Financial Services",
    "sector_name": "XLF",
    "market_change_1d": 0.5480715084158039,
    "market_change_5d": 1.5045200833746275,
    "market_change_20d": 4.746644606840866,
    "market_trend": "up",
    "sector_change_1d": -0.2214052114171472,
    "sector_change_5d": 0.16428117842144374,
    "sector_change_20d": 0.028950760955148702,
    "sector_trend": "neutral",
    "OverallRating": 83.2,
    "AITicker": "KeyCorp, a financial services provider, offers banking products and services primarily in the United States.",
    "AIComment": "KeyCorp (KEY) shows moderate short-term trading potential given the overall market's upward trend and the stock's recent performance. The neutral sector trend and the stock's MACD nearing a bullish crossover suggest cautious optimism. However, the relatively low RSI and slight underperformance compared to the broader market might limit upside momentum.",
    "AIScore": 65,
    "SL": 21.05,
    "TP": 22.55,
    "SL10": 9.71,
    "TP10": 10.4,
    "Normalize": 23.1
  },
  {
    "ticker": "JNJ",
    "name": "Johnson & Johnson",
    "marketCap": 554598727680,
    "revenueGrowth": 0.099,
    "debtToEquity": 67.73,
    "trailingPE": 26.727379,
    "momentum_2m": -0.07261600377566446,
    "momentum_1w": 0.006421462661458932,
    "FundamentalFilterRating": 66,
    "price": 230.39010620117188,
    "RSI (14)": 57.87,
    "EMA (20)": 228.18,
    "MACD (12,26,9)": 1.5814,
    "MACD_Signal (12,26,9)": 0.9209,
    "percent_change": -1.69,
    "TechFilterRating": 100.0,
    "news_sentiment_percent": 83.3,
    "social_sentiment_percent": null,
    "sector": "Healthcare",
    "sector_name": "XLV",
    "market_change_1d": 0.5480715084158039,
    "market_change_5d": 1.5045200833746275,
    "market_change_20d": 4.746644606840866,
    "market_trend": "up",
    "sector_change_1d": -0.5203808009026756,
    "sector_change_5d": 2.326378919331762,
    "sector_change_20d": 3.938375597425803,
    "sector_trend": "up",
    "OverallRating": 83.1,
    "AITicker": "Johnson & Johnson, a major player in the healthcare sector, primarily focuses on manufacturing pharmaceuticals, medical devices, and consumer health products.",
    "AIComment": "Johnson & Johnson shows a stable outlook for short-term trading (2-10 days) with a positive sector and market trend. The stock's recent performance, including a slight weekly momentum increase and positive MACD above its signal, suggests potential for modest gains. However, the negative 2-month momentum and a slight recent price drop indicate some caution is warranted.",
    "AIScore": 65,
    "SL": 223.62,
    "TP": 239.61,
    "SL10": 9.71,
    "TP10": 10.4,
    "Normalize": 2.2
  },
  {
    "ticker": "CFG",
    "name": "Citizens Financial Group",
    "marketCap": 26768427008,
    "revenueGrowth": 0.138,
    "debtToEquity": null,
    "trailingPE": 15.000001,
    "momentum_2m": 0.0592356800928191,
    "momentum_1w": 0.0349901797741583,
    "FundamentalFilterRating": 83,
    "price": 63.31999969482422,
    "RSI (14)": 44.84,
    "EMA (20)": 62.85,
    "MACD (12,26,9)": -0.4533,
    "MACD_Signal (12,26,9)": -0.5674,
    "percent_change": 0.68,
    "TechFilterRating": 100.0,
    "news_sentiment_percent": 83.3,
    "social_sentiment_percent": null,
    "sector": "Financial Services",
    "sector_name": "XLF",
    "market_change_1d": 0.5480715084158039,
    "market_change_5d": 1.5045200833746275,
    "market_change_20d": 4.746644606840866,
    "market_trend": "up",
    "sector_change_1d": -0.2117766626157258,
    "sector_change_5d": 0.17394694562862245,
    "sector_change_20d": 0.038603468893128046,
    "sector_trend": "neutral",
    "OverallRating": 88.8,
    "AITicker": "Citizens Financial Group, a financial services provider, offers banking and financial products to individuals and businesses.",
    "AIComment": "Citizens Financial Group (CFG) shows a neutral short-term trading outlook. The overall market is trending up, which is favorable, but the financial sector remains neutral, potentially limiting sector-specific gains. The stock's recent performance and technical indicators like a negative MACD but a positive news sentiment suggest mixed signals, making it a moderate risk for a 2-10 day trade.",
    "AIScore": 55,
    "SL": 61.59,
    "TP": 65.85,
    "SL10": 9.73,
    "TP10": 10.4,
    "Normalize": 7.9
  },
  {
    "ticker": "MO",
    "name": "Altria",
    "marketCap": 121000312832,
    "revenueGrowth": 0.053,
    "debtToEquity": null,
    "trailingPE": 15.127349,
    "momentum_2m": 0.06712277497761532,
    "momentum_1w": -0.017091727012568447,
    "FundamentalFilterRating": 66,
    "price": 72.41000366210938,
    "RSI (14)": 48.57,
    "EMA (20)": 71.44,
    "MACD (12,26,9)": 1.5633,
    "MACD_Signal (12,26,9)": 1.4956,
    "percent_change": -2.02,
    "TechFilterRating": 100.0,
    "news_sentiment_percent": 83.3,
    "social_sentiment_percent": null,
    "sector": "Consumer Defensive",
    "sector_name": "XLP",
    "market_change_1d": 0.5480715084158039,
    "market_change_5d": 1.5045200833746275,
    "market_change_20d": 4.746644606840866,
    "market_trend": "up",
    "sector_change_1d": -1.2971769621803353,
    "sector_change_5d": -2.5611228621153503,
    "sector_change_20d": 1.6516889371365195,
    "sector_trend": "down",
    "OverallRating": 83.1,
    "AITicker": "Altria Group, Inc., known as MO, is a company primarily involved in the manufacture and sale of tobacco products and related items.",
    "AIComment": "Altria's stock shows mixed signals for a short-term trade. While the overall market is trending up, the consumer defensive sector, to which Altria belongs, is trending down. The stock's recent performance and technical indicators like a negative weekly momentum and a MACD close to its signal suggest caution. However, positive news sentiment could provide some support.",
    "AIScore": 45,
    "SL": 70.24,
    "TP": 75.31,
    "SL10": 9.7,
    "TP10": 10.4,
    "Normalize": 6.9
  }
]