[
  {
    "ticker": "UNP",
    "name": "Union Pacific Corporation",
    "marketCap": 165114626048,
    "revenueGrowth": 0.032,
    "debtToEquity": 162.246,
    "trailingPE": 22.889301,
    "momentum_2m": 0.04170884262168362,
    "momentum_1w": 0.02410153736403009,
    "FundamentalFilterRating": 83,
    "price": 278.19000244140625,
    "RSI (14)": 62.15,
    "EMA (20)": 268.86,
    "MACD (12,26,9)": 0.996,
    "MACD_Signal (12,26,9)": 0.1551,
    "percent_change": 2.62,
    "TechFilterRating": 100.0,
    "news_sentiment_percent": 75.0,
    "social_sentiment_percent": null,
    "sector": "Industrials",
    "sector_name": "XLI",
    "market_change_1d": 0.02460524140346365,
    "market_change_5d": 2.2758938082666047,
    "market_change_20d": 5.3534266348988835,
    "market_trend": "up",
    "sector_change_1d": 0.19219245508483862,
    "sector_change_5d": 3.4935337334160987,
    "sector_change_20d": 2.1376762607487665,
    "sector_trend": "up",
    "OverallRating": 86.0,
    "AITicker": "Union Pacific Corporation (UNP) is a major freight hauling railroad that operates in the United States, primarily serving the Western two-thirds of the country.",
    "AIComment": "Union Pacific Corporation shows a positive short-term trading outlook, supported by an upward trend in both the broader market and the industrials sector. The stock's recent performance, including a 2.62% price increase and positive momentum indicators such as RSI and MACD, suggests continued strength. The positive news sentiment further bolsters the case for a bullish outlook over the next 2-10 days.",
    "AIScore": 85,
    "SL": 269.84,
    "TP": 289.32,
    "SL10": 9.7,
    "TP10": 10.4,
    "Normalize": 1.8
  },
  {
    "ticker": "TSLA",
    "name": "Tesla, Inc.",
    "marketCap": 1658414956544,
    "revenueGrowth": 0.158,
    "debtToEquity": 18.738,
    "trailingPE": 408.8611,
    "momentum_2m": 0.09483784415696439,
    "momentum_1w": 0.09269759058308646,
    "FundamentalFilterRating": 66,
    "price": 441.55499267578125,
    "RSI (14)": 64.44,
    "EMA (20)": 416.22,
    "MACD (12,26,9)": 11.5728,
    "MACD_Signal (12,26,9)": 10.9283,
    "percent_change": 1.84,
    "TechFilterRating": 100.0,
    "news_sentiment_percent": 91.7,
    "social_sentiment_percent": null,
    "sector": "Consumer Cyclical",
    "sector_name": "XLY",
    "market_change_1d": 0.02460524140346365,
    "market_change_5d": 2.2758938082666047,
    "market_change_20d": 5.3534266348988835,
    "market_trend": "up",
    "sector_change_1d": 1.645043128914092,
    "sector_change_5d": 5.550727813603729,
    "sector_change_20d": 3.7646343892621115,
    "sector_trend": "up",
    "OverallRating": 85.9,
    "AITicker": "Tesla, Inc. is an American electric vehicle and clean energy company.",
    "AIComment": "Tesla shows a strong short-term trading potential given its alignment with the upward trends in both the market and its sector. The positive momentum indicators and a high news sentiment further support a bullish outlook. However, its high trailing PE ratio suggests a relatively higher valuation risk.",
    "AIScore": 85,
    "SL": 428.31,
    "TP": 459.22,
    "SL10": 9.7,
    "TP10": 10.4,
    "Normalize": 1.1
  },
  {
    "ticker": "NUE",
    "name": "Nucor",
    "marketCap": 55828414464,
    "revenueGrowth": 0.213,
    "debtToEquity": 31.595,
    "trailingPE": 24.343596,
    "momentum_2m": 0.36222007303614867,
    "momentum_1w": 0.1055788757190772,
    "FundamentalFilterRating": 83,
    "price": 245.08999633789062,
    "RSI (14)": 60.35,
    "EMA (20)": 229.18,
    "MACD (12,26,9)": 4.2926,
    "MACD_Signal (12,26,9)": 3.2439,
    "percent_change": 2.0,
    "TechFilterRating": 100.0,
    "news_sentiment_percent": 66.7,
    "social_sentiment_percent": null,
    "sector": "Basic Materials",
    "sector_name": "XLB",
    "market_change_1d": 0.02460524140346365,
    "market_change_5d": 2.2758938082666047,
    "market_change_20d": 5.3534266348988835,
    "market_trend": "up",
    "sector_change_1d": 0.5981495988208962,
    "sector_change_5d": 4.598281426018436,
    "sector_change_20d": -0.20428668057670407,
    "sector_trend": "up",
    "OverallRating": 83.2,
    "AITicker": "Nucor is a leading manufacturer of steel and steel products, primarily serving the construction, automotive, and energy sectors.",
    "AIComment": "Nucor appears to be a favorable short-term trading opportunity given the positive trends in both the market and its sector. The company's stock has shown strong momentum and positive technical indicators such as a rising MACD above its signal line and a robust RSI. The positive news sentiment further supports the bullish outlook for the next 2-10 days.",
    "AIScore": 85,
    "SL": 237.74,
    "TP": 259.8,
    "SL10": 9.7,
    "TP10": 10.6,
    "Normalize": 2.0
  },
  {
    "ticker": "WDC",
    "name": "Western Digital",
    "marketCap": 183715577856,
    "revenueGrowth": 0.455,
    "debtToEquity": 17.81,
    "trailingPE": 31.954435,
    "momentum_2m": 0.9744340415795296,
    "momentum_1w": 0.16937256312980997,
    "FundamentalFilterRating": 83,
    "price": 532.5250244140625,
    "RSI (14)": 61.07,
    "EMA (20)": 473.57,
    "MACD (12,26,9)": 22.6786,
    "MACD_Signal (12,26,9)": 19.394,
    "percent_change": 1.5,
    "TechFilterRating": 100.0,
    "news_sentiment_percent": 75.0,
    "social_sentiment_percent": null,
    "sector": "Technology",
    "sector_name": "XLK",
    "market_change_1d": 0.02460524140346365,
    "market_change_5d": 2.2758938082666047,
    "market_change_20d": 5.3534266348988835,
    "market_trend": "up",
    "sector_change_1d": -0.6508598007060717,
    "sector_change_5d": 6.173511733034265,
    "sector_change_20d": 16.525176082648983,
    "sector_trend": "up",
    "OverallRating": 86.0,
    "AITicker": "Western Digital is a technology company specializing in data storage solutions, including hard drives and solid state drives.",
    "AIComment": "Western Digital shows a promising short-term trading opportunity given the positive momentum in both the broader market and technology sector. The stock's recent performance, with a price above its EMA(20) and a positive MACD divergence, suggests upward potential. The high news sentiment and reasonable RSI also support a bullish outlook for the next 2-10 days.",
    "AIScore": 82,
    "SL": 516.55,
    "TP": 564.48,
    "SL10": 9.7,
    "TP10": 10.6,
    "Normalize": 0.9
  },
  {
    "ticker": "DAL",
    "name": "Delta Air Lines",
    "marketCap": 53495767040,
    "revenueGrowth": 0.129,
    "debtToEquity": 105.021,
    "trailingPE": 11.886862,
    "momentum_2m": 0.27067744100464175,
    "momentum_1w": 0.20166765768475137,
    "FundamentalFilterRating": 83,
    "price": 81.36000061035156,
    "RSI (14)": 69.1,
    "EMA (20)": 72.91,
    "MACD (12,26,9)": 2.3879,
    "MACD_Signal (12,26,9)": 1.3734,
    "percent_change": 2.48,
    "TechFilterRating": 100.0,
    "news_sentiment_percent": 75.0,
    "social_sentiment_percent": null,
    "sector": "Industrials",
    "sector_name": "XLI",
    "market_change_1d": 0.02460524140346365,
    "market_change_5d": 2.2758938082666047,
    "market_change_20d": 5.3534266348988835,
    "market_trend": "up",
    "sector_change_1d": 0.2180089600518187,
    "sector_change_5d": 3.5202008944214658,
    "sector_change_20d": 2.163994058192764,
    "sector_trend": "up",
    "OverallRating": 86.0,
    "AITicker": "Delta Air Lines, a major American airline, operates extensive domestic and international flights.",
    "AIComment": "Delta Air Lines (DAL) shows strong short-term trading potential, supported by positive market and sector trends. The stock's recent performance, with a significant momentum and a high RSI, suggests it might be slightly overbought but still holds upward potential due to positive news sentiment and robust sector growth. Caution is advised due to the high RSI, which could indicate a pullback.",
    "AIScore": 78,
    "SL": 78.92,
    "TP": 85.43,
    "SL10": 9.7,
    "TP10": 10.5,
    "Normalize": 6.1
  },
  {
    "ticker": "NXPI",
    "name": "NXP Semiconductors",
    "marketCap": 83131146240,
    "revenueGrowth": 0.122,
    "debtToEquity": 103.991,
    "trailingPE": 31.50909,
    "momentum_2m": 0.472587798090341,
    "momentum_1w": 0.11890033430582103,
    "FundamentalFilterRating": 83,
    "price": 329.2200012207031,
    "RSI (14)": 60.87,
    "EMA (20)": 296.39,
    "MACD (12,26,9)": 17.017,
    "MACD_Signal (12,26,9)": 15.0037,
    "percent_change": -1.04,
    "TechFilterRating": 100.0,
    "news_sentiment_percent": 75.0,
    "social_sentiment_percent": null,
    "sector": "Technology",
    "sector_name": "XLK",
    "market_change_1d": 0.02460524140346365,
    "market_change_5d": 2.2758938082666047,
    "market_change_20d": 5.3534266348988835,
    "market_trend": "up",
    "sector_change_1d": -0.6589614479448613,
    "sector_change_5d": 6.164853577196805,
    "sector_change_20d": 16.515673777252427,
    "sector_trend": "up",
    "OverallRating": 86.0,
    "AITicker": "NXP Semiconductors is a company specializing in high performance mixed signal solutions, primarily serving the automotive and industrial markets.",
    "AIComment": "NXP Semiconductors appears to be a favorable short-term trading opportunity, given the positive trends in both the broader market and the technology sector. The company's recent momentum and positive news sentiment further support potential gains. However, a slight recent price decline and a high debt-to-equity ratio suggest some caution is warranted.",
    "AIScore": 78,
    "SL": 319.34,
    "TP": 348.97,
    "SL10": 9.7,
    "TP10": 10.6,
    "Normalize": 1.5
  },
  {
    "ticker": "SPG",
    "name": "Simon Property Group",
    "marketCap": 78971166720,
    "revenueGrowth": 0.193,
    "debtToEquity": 457.473,
    "trailingPE": 14.452712,
    "momentum_2m": 0.03422015042707671,
    "momentum_1w": 0.03412822715677022,
    "FundamentalFilterRating": 83,
    "price": 207.78500366210938,
    "RSI (14)": 53.86,
    "EMA (20)": 203.33,
    "MACD (12,26,9)": 1.0574,
    "MACD_Signal (12,26,9)": 0.4839,
    "percent_change": 0.41,
    "TechFilterRating": 75.0,
    "news_sentiment_percent": 100.0,
    "social_sentiment_percent": null,
    "sector": "Real Estate",
    "sector_name": "XLRE",
    "market_change_1d": 0.02460524140346365,
    "market_change_5d": 2.2758938082666047,
    "market_change_20d": 5.3534266348988835,
    "market_trend": "up",
    "sector_change_1d": 0.1230156705480212,
    "sector_change_5d": 1.877562104514885,
    "sector_change_20d": 1.9471636192381236,
    "sector_trend": "up",
    "OverallRating": 86.0,
    "AITicker": "Simon Property Group, a real estate company, primarily involved in owning, developing, and managing retail real estate properties.",
    "AIComment": "Simon Property Group (SPG) shows a positive alignment with the upward trends in both the broader market and its specific real estate sector. With a recent price increase and strong news sentiment, the stock appears favorable for a short-term trade. The technical indicators such as a rising MACD above its signal and a moderate RSI suggest continued momentum.",
    "AIScore": 78,
    "SL": 201.55,
    "TP": 216.1,
    "SL10": 9.7,
    "TP10": 10.4,
    "Normalize": 2.4
  },
  {
    "ticker": "UAL",
    "name": "United Airlines Holdings",
    "marketCap": 36544929792,
    "revenueGrowth": 0.106,
    "debtToEquity": 195.081,
    "trailingPE": 10.06211,
    "momentum_2m": 0.09093113283093124,
    "momentum_1w": 0.26340886165447763,
    "FundamentalFilterRating": 83,
    "price": 112.44000244140625,
    "RSI (14)": 67.78,
    "EMA (20)": 97.69,
    "MACD (12,26,9)": 3.0331,
    "MACD_Signal (12,26,9)": 1.5145,
    "percent_change": 6.16,
    "TechFilterRating": 100.0,
    "news_sentiment_percent": 75.0,
    "social_sentiment_percent": null,
    "sector": "Industrials",
    "sector_name": "XLI",
    "market_change_1d": 0.02460524140346365,
    "market_change_5d": 2.2758938082666047,
    "market_change_20d": 5.3534266348988835,
    "market_trend": "up",
    "sector_change_1d": 0.19219245508483862,
    "sector_change_5d": 3.4935337334160987,
    "sector_change_20d": 2.1376762607487665,
    "sector_trend": "up",
    "OverallRating": 86.0,
    "AITicker": "United Airlines Holdings, a major American airline, operates a large domestic and international route network.",
    "AIComment": "United Airlines Holdings shows strong short-term trading potential, supported by positive market and sector trends. The stock's recent performance, indicated by a significant momentum and a high RSI, suggests it might be slightly overbought but still holds upward potential due to positive news sentiment and robust sector growth. Caution is advised due to its high debt-to-equity ratio.",
    "AIScore": 78,
    "SL": 109.07,
    "TP": 116.94,
    "SL10": 9.7,
    "TP10": 10.4,
    "Normalize": 4.4
  },
  {
    "ticker": "AMD",
    "name": "Advanced Micro Devices",
    "marketCap": 810326949888,
    "revenueGrowth": 0.378,
    "debtToEquity": 6.005,
    "trailingPE": 164.55298,
    "momentum_2m": 1.5020140188495446,
    "momentum_1w": 0.20021742991938885,
    "FundamentalFilterRating": 66,
    "price": 496.409912109375,
    "RSI (14)": 67.55,
    "EMA (20)": 429.37,
    "MACD (12,26,9)": 33.6343,
    "MACD_Signal (12,26,9)": 27.9565,
    "percent_change": -1.48,
    "TechFilterRating": 100.0,
    "news_sentiment_percent": 91.7,
    "social_sentiment_percent": null,
    "sector": "Technology",
    "sector_name": "XLK",
    "market_change_1d": 0.02460524140346365,
    "market_change_5d": 2.2758938082666047,
    "market_change_20d": 5.3534266348988835,
    "market_trend": "up",
    "sector_change_1d": -0.6319532098965408,
    "sector_change_5d": 6.193717032618351,
    "sector_change_20d": 16.54735135078702,
    "sector_trend": "up",
    "OverallRating": 85.9,
    "AITicker": "Advanced Micro Devices (AMD) is a prominent technology company specializing in semiconductors, including CPUs and GPUs.",
    "AIComment": "AMD shows potential for a short-term trade given the positive trends in both the broader market and technology sector. The company's recent price momentum and strong news sentiment further support this outlook. However, the slightly high trailing PE and a minor recent price decline suggest some caution is warranted.",
    "AIScore": 78,
    "SL": 481.52,
    "TP": 526.19,
    "SL10": 9.7,
    "TP10": 10.6,
    "Normalize": 1.0
  },
  {
    "ticker": "BBY",
    "name": "Best Buy",
    "marketCap": 13345432576,
    "revenueGrowth": -0.01,
    "debtToEquity": 139.474,
    "trailingPE": 12.56746,
    "momentum_2m": 0.04423715699346764,
    "momentum_1w": 0.06847693533312937,
    "FundamentalFilterRating": 66,
    "price": 63.900001525878906,
    "RSI (14)": 68.51,
    "EMA (20)": 59.8,
    "MACD (12,26,9)": 0.872,
    "MACD_Signal (12,26,9)": 0.1564,
    "percent_change": 1.08,
    "TechFilterRating": 100.0,
    "news_sentiment_percent": 91.7,
    "social_sentiment_percent": null,
    "sector": "Consumer Cyclical",
    "sector_name": "XLY",
    "market_change_1d": 0.02460524140346365,
    "market_change_5d": 2.2758938082666047,
    "market_change_20d": 5.3534266348988835,
    "market_trend": "up",
    "sector_change_1d": 1.6408595763434564,
    "sector_change_5d": 5.546383509099684,
    "sector_change_20d": 3.760363597597527,
    "sector_trend": "up",
    "OverallRating": 85.9,
    "AITicker": "Best Buy, a leading retailer specializing in consumer electronics and related merchandise.",
    "AIComment": "Best Buy shows a positive short-term trading outlook, supported by an upward trend in both the market and its sector. The stock's recent performance, including a 1.08% price increase and strong momentum indicators, suggests potential for further gains. The high RSI indicates it might be slightly overbought, which could limit upside potential but overall, the environment appears favorable.",
    "AIScore": 78,
    "SL": 61.98,
    "TP": 66.46,
    "SL10": 9.7,
    "TP10": 10.4,
    "Normalize": 7.8
  },
  {
    "ticker": "MNST",
    "name": "Monster Beverage",
    "marketCap": 87512170496,
    "revenueGrowth": 0.269,
    "debtToEquity": 1.082,
    "trailingPE": 43.227055,
    "momentum_2m": 0.10387374848183883,
    "momentum_1w": 0.03624788579180516,
    "FundamentalFilterRating": 83,
    "price": 89.5250015258789,
    "RSI (14)": 78.55,
    "EMA (20)": 84.26,
    "MACD (12,26,9)": 2.8137,
    "MACD_Signal (12,26,9)": 2.4698,
    "percent_change": 2.41,
    "TechFilterRating": 75.0,
    "news_sentiment_percent": 91.7,
    "social_sentiment_percent": null,
    "sector": "Consumer Defensive",
    "sector_name": "XLP",
    "market_change_1d": 0.02460524140346365,
    "market_change_5d": 2.2758938082666047,
    "market_change_20d": 5.3534266348988835,
    "market_trend": "up",
    "sector_change_1d": 1.4496032541380321,
    "sector_change_5d": -1.4492925728031625,
    "sector_change_20d": 2.1212067226094256,
    "sector_trend": "down",
    "OverallRating": 83.2,
    "AITicker": "Monster Beverage Corporation, known for its energy drinks including the flagship Monster Energy line.",
    "AIComment": "Monster Beverage (MNST) shows strong short-term trading potential, supported by a positive market trend and a significant upward momentum in its stock price. Despite the sector's downward trend, MNST's robust revenue growth and high news sentiment indicate resilience. However, its high RSI suggests it might be overbought, which could limit upside potential in the very short term.",
    "AIScore": 78,
    "SL": 86.84,
    "TP": 93.11,
    "SL10": 9.7,
    "TP10": 10.4,
    "Normalize": 5.6
  },
  {
    "ticker": "EXPE",
    "name": "Expedia Group",
    "marketCap": 27340429312,
    "revenueGrowth": 0.147,
    "debtToEquity": 256.536,
    "trailingPE": 20.105473,
    "momentum_2m": 0.07057397808075994,
    "momentum_1w": 0.05951161939044325,
    "FundamentalFilterRating": 83,
    "price": 227.72500610351562,
    "RSI (14)": 35.38,
    "EMA (20)": 227.19,
    "MACD (12,26,9)": -6.4855,
    "MACD_Signal (12,26,9)": -6.6542,
    "percent_change": 2.13,
    "TechFilterRating": 100.0,
    "news_sentiment_percent": 91.7,
    "social_sentiment_percent": null,
    "sector": "Consumer Cyclical",
    "sector_name": "XLY",
    "market_change_1d": 0.02460524140346365,
    "market_change_5d": 2.2758938082666047,
    "market_change_20d": 5.3534266348988835,
    "market_trend": "up",
    "sector_change_1d": 1.6408595763434564,
    "sector_change_5d": 5.546383509099684,
    "sector_change_20d": 3.760363597597527,
    "sector_trend": "up",
    "OverallRating": 91.6,
    "AITicker": "Expedia Group, a leading online travel company, provides travel products and services.",
    "AIComment": "Expedia Group shows potential for a short-term trade, given the positive market and sector trends. The recent momentum and positive news sentiment align with the overall upward movement in the consumer cyclical sector. However, caution is advised due to its high debt-to-equity ratio and a relatively low RSI, suggesting possible overvaluation or short-term pullbacks.",
    "AIScore": 72,
    "SL": 222.65,
    "TP": 236.83,
    "SL10": 9.78,
    "TP10": 10.4,
    "Normalize": 2.2
  },
  {
    "ticker": "MPWR",
    "name": "Monolithic Power Systems",
    "marketCap": 79415205888,
    "revenueGrowth": 0.261,
    "debtToEquity": 0.543,
    "trailingPE": 115.70723,
    "momentum_2m": 0.41754784833309233,
    "momentum_1w": 0.10102789970729442,
    "FundamentalFilterRating": 83,
    "price": 1615.8199462890625,
    "RSI (14)": 47.38,
    "EMA (20)": 1584.98,
    "MACD (12,26,9)": 2.1324,
    "MACD_Signal (12,26,9)": -3.0018,
    "percent_change": -2.84,
    "TechFilterRating": 100.0,
    "news_sentiment_percent": 75.0,
    "social_sentiment_percent": null,
    "sector": "Technology",
    "sector_name": "XLK",
    "market_change_1d": 0.02460524140346365,
    "market_change_5d": 2.2758938082666047,
    "market_change_20d": 5.3534266348988835,
    "market_trend": "up",
    "sector_change_1d": -0.6481565043741089,
    "sector_change_5d": 6.176400720943409,
    "sector_change_20d": 16.52834673999393,
    "sector_trend": "up",
    "OverallRating": 86.0,
    "AITicker": "Monolithic Power Systems, a technology company, specializes in high-performance power solutions.",
    "AIComment": "Monolithic Power Systems (MPWR) shows potential for a short-term trade, given the positive trends in both the broader market and technology sector. The company's recent momentum and positive news sentiment align with an upward sector trend, suggesting a favorable environment. However, the stock's recent price decline and a moderate RSI indicate some caution is warranted.",
    "AIScore": 72,
    "SL": 1567.35,
    "TP": 1712.77,
    "SL10": 9.7,
    "TP10": 10.6,
    "Normalize": 0.3
  },
  {
    "ticker": "TGT",
    "name": "Target Corporation",
    "marketCap": 58650161152,
    "revenueGrowth": 0.067,
    "debtToEquity": 117.152,
    "trailingPE": 17.03628,
    "momentum_2m": 0.15185180824797828,
    "momentum_1w": 0.014893089239873314,
    "FundamentalFilterRating": 83,
    "price": 129.26499938964844,
    "RSI (14)": 50.39,
    "EMA (20)": 125.38,
    "MACD (12,26,9)": -0.3008,
    "MACD_Signal (12,26,9)": -0.9447,
    "percent_change": 3.06,
    "TechFilterRating": 100.0,
    "news_sentiment_percent": 75.0,
    "social_sentiment_percent": null,
    "sector": "Consumer Defensive",
    "sector_name": "XLP",
    "market_change_1d": 0.02460524140346365,
    "market_change_5d": 2.2758938082666047,
    "market_change_20d": 5.3534266348988835,
    "market_trend": "up",
    "sector_change_1d": 1.4496032541380321,
    "sector_change_5d": -1.4492925728031625,
    "sector_change_20d": 2.1212067226094256,
    "sector_trend": "down",
    "OverallRating": 86.0,
    "AITicker": "Target Corporation, a major retailer in the United States, offers a wide range of products including household essentials, apparel, and food.",
    "AIComment": "Target Corporation (TGT) shows a positive short-term trading opportunity, with a recent price increase and a market trend that is upward, despite a downward trend in the Consumer Defensive sector. The stock's positive momentum and favorable news sentiment further support potential gains. However, caution is advised due to the sector's negative performance.",
    "AIScore": 72,
    "SL": 125.39,
    "TP": 135.73,
    "SL10": 9.7,
    "TP10": 10.5,
    "Normalize": 3.9
  },
  {
    "ticker": "UDR",
    "name": "UDR, Inc.",
    "marketCap": 14149621760,
    "revenueGrowth": 0.042,
    "debtToEquity": 142.368,
    "trailingPE": 25.97891,
    "momentum_2m": 0.03252185634964788,
    "momentum_1w": 0.021096192993482532,
    "FundamentalFilterRating": 83,
    "price": 38.224998474121094,
    "RSI (14)": 67.0,
    "EMA (20)": 37.11,
    "MACD (12,26,9)": 0.7072,
    "MACD_Signal (12,26,9)": 0.6742,
    "percent_change": 0.51,
    "TechFilterRating": 100.0,
    "news_sentiment_percent": 75.0,
    "social_sentiment_percent": null,
    "sector": "Real Estate",
    "sector_name": "XLRE",
    "market_change_1d": 0.02460524140346365,
    "market_change_5d": 2.2758938082666047,
    "market_change_20d": 5.3534266348988835,
    "market_trend": "up",
    "sector_change_1d": 0.1230156705480212,
    "sector_change_5d": 1.877562104514885,
    "sector_change_20d": 1.9471636192381236,
    "sector_trend": "up",
    "OverallRating": 86.0,
    "AITicker": "UDR, Inc. is a real estate investment trust that owns, operates, acquires, and develops apartment communities primarily in the United States.",
    "AIComment": "UDR, Inc. shows a positive short-term trading outlook, supported by an upward trend in both the overall market and the real estate sector. The stock's recent performance, including a positive momentum and a rising MACD above its signal, suggests continued strength. However, a relatively high RSI indicates potential overbought conditions, which could limit the upside or increase volatility.",
    "AIScore": 72,
    "SL": 37.08,
    "TP": 39.75,
    "SL10": 9.7,
    "TP10": 10.4,
    "Normalize": 13.1
  },
  {
    "ticker": "FOXA",
    "name": "Fox Corporation (Class A)",
    "marketCap": 27526406144,
    "revenueGrowth": -0.086,
    "debtToEquity": 67.867,
    "trailingPE": 17.239475,
    "momentum_2m": 0.15920679534836402,
    "momentum_1w": 0.014872177212801985,
    "FundamentalFilterRating": 66,
    "price": 65.51000213623047,
    "RSI (14)": 62.04,
    "EMA (20)": 64.53,
    "MACD (12,26,9)": 0.311,
    "MACD_Signal (12,26,9)": 0.2904,
    "percent_change": 0.85,
    "TechFilterRating": 100.0,
    "news_sentiment_percent": 91.7,
    "social_sentiment_percent": null,
    "sector": "Communication Services",
    "sector_name": "XLC",
    "market_change_1d": 0.02460524140346365,
    "market_change_5d": 2.2758938082666047,
    "market_change_20d": 5.3534266348988835,
    "market_trend": "up",
    "sector_change_1d": 0.874075707625499,
    "sector_change_5d": 0.6128606765853917,
    "sector_change_20d": 0.6997819080723611,
    "sector_trend": "neutral",
    "OverallRating": 85.9,
    "AITicker": "Fox Corporation (Class A), a major player in the communication services sector, primarily focuses on news, sports, and entertainment broadcasting.",
    "AIComment": "Fox Corporation shows a positive short-term trading outlook, supported by an upward market trend and a stable sector trend. The stock's recent performance, including a slight increase in momentum and positive news sentiment, suggests potential for continued growth. However, investors should be cautious of the relatively high debt-to-equity ratio and the recent revenue decline.",
    "AIScore": 72,
    "SL": 63.54,
    "TP": 68.79,
    "SL10": 9.7,
    "TP10": 10.5,
    "Normalize": 7.6
  },
  {
    "ticker": "NWSA",
    "name": "News Corp (Class A)",
    "marketCap": 14566464512,
    "revenueGrowth": 0.088,
    "debtToEquity": 31.559,
    "trailingPE": 33.77848,
    "momentum_2m": 0.11791878231402042,
    "momentum_1w": 0.016958829981165602,
    "FundamentalFilterRating": 83,
    "price": 26.69499969482422,
    "RSI (14)": 55.25,
    "EMA (20)": 26.3,
    "MACD (12,26,9)": -0.0322,
    "MACD_Signal (12,26,9)": -0.0377,
    "percent_change": 1.89,
    "TechFilterRating": 100.0,
    "news_sentiment_percent": 66.7,
    "social_sentiment_percent": null,
    "sector": "Communication Services",
    "sector_name": "XLC",
    "market_change_1d": 0.02460524140346365,
    "market_change_5d": 2.2758938082666047,
    "market_change_20d": 5.3534266348988835,
    "market_trend": "up",
    "sector_change_1d": 0.874075707625499,
    "sector_change_5d": 0.6128606765853917,
    "sector_change_20d": 0.6997819080723611,
    "sector_trend": "neutral",
    "OverallRating": 83.2,
    "AITicker": "News Corp (Class A), a global diversified media and information services company.",
    "AIComment": "News Corp shows a positive short-term trading opportunity, with a recent price increase and a market trend that is upward. The neutral sector trend and the company's moderate RSI suggest some caution, but the positive momentum and news sentiment indicate potential for further gains in the next 2-10 days.",
    "AIScore": 72,
    "SL": 25.89,
    "TP": 28.03,
    "SL10": 9.7,
    "TP10": 10.5,
    "Normalize": 18.7
  },
  {
    "ticker": "ULTA",
    "name": "Ulta Beauty",
    "marketCap": 22411085824,
    "revenueGrowth": 0.118,
    "debtToEquity": 77.835,
    "trailingPE": 19.976997,
    "momentum_2m": -0.243116730953425,
    "momentum_1w": 0.06406257941344862,
    "FundamentalFilterRating": 66,
    "price": 512.52001953125,
    "RSI (14)": 39.47,
    "EMA (20)": 511.47,
    "MACD (12,26,9)": -7.4921,
    "MACD_Signal (12,26,9)": -9.4199,
    "percent_change": -0.68,
    "TechFilterRating": 100.0,
    "news_sentiment_percent": 91.7,
    "social_sentiment_percent": null,
    "sector": "Consumer Cyclical",
    "sector_name": "XLY",
    "market_change_1d": 0.02460524140346365,
    "market_change_5d": 2.2758938082666047,
    "market_change_20d": 5.3534266348988835,
    "market_trend": "up",
    "sector_change_1d": 1.645043128914092,
    "sector_change_5d": 5.550727813603729,
    "sector_change_20d": 3.7646343892621115,
    "sector_trend": "up",
    "OverallRating": 85.9,
    "AITicker": "Ulta Beauty is a leading beauty retailer in the United States, offering cosmetics, fragrance, skincare, haircare products, and salon services.",
    "AIComment": "Ulta Beauty (ULTA) shows potential for a short-term trade, given the positive trends in both the broader market and its specific sector. The stock's recent performance, with a slight increase in momentum over the past week and a positive news sentiment, aligns with these upward trends. However, caution is advised due to its current RSI and negative MACD values, suggesting potential volatility.",
    "AIScore": 65,
    "SL": 501.24,
    "TP": 533.02,
    "SL10": 9.78,
    "TP10": 10.4,
    "Normalize": 1.0
  },
  {
    "ticker": "KEY",
    "name": "KeyCorp",
    "marketCap": 23359641600,
    "revenueGrowth": 0.118,
    "debtToEquity": null,
    "trailingPE": 13.217792,
    "momentum_2m": 0.040569918168709584,
    "momentum_1w": 0.029875716908253525,
    "FundamentalFilterRating": 83,
    "price": 21.55500030517578,
    "RSI (14)": 39.1,
    "EMA (20)": 21.5,
    "MACD (12,26,9)": -0.0926,
    "MACD_Signal (12,26,9)": -0.1449,
    "percent_change": -0.99,
    "TechFilterRating": 100.0,
    "news_sentiment_percent": 75.0,
    "social_sentiment_percent": null,
    "sector": "Financial Services",
    "sector_name": "XLF",
    "market_change_1d": 0.02460524140346365,
    "market_change_5d": 2.2758938082666047,
    "market_change_20d": 5.3534266348988835,
    "market_trend": "up",
    "sector_change_1d": -0.8003801601599081,
    "sector_change_5d": 0.6555829925114054,
    "sector_change_20d": -0.8003801601599081,
    "sector_trend": "neutral",
    "OverallRating": 86.0,
    "AITicker": "KeyCorp, a financial services provider, offers banking products and services primarily in the United States.",
    "AIComment": "KeyCorp (KEY) shows a neutral short-term trading outlook for the next 2-10 days. The overall market is trending upwards, which is positive, but the financial sector remains neutral, potentially limiting sector-specific gains. The stock's technical indicators like a below-average RSI and negative MACD divergence suggest caution, despite recent positive news sentiment.",
    "AIScore": 55,
    "SL": 21.07,
    "TP": 22.42,
    "SL10": 9.77,
    "TP10": 10.4,
    "Normalize": 23.2
  },
  {
    "ticker": "CFG",
    "name": "Citizens Financial Group",
    "marketCap": 26588702720,
    "revenueGrowth": 0.138,
    "debtToEquity": null,
    "trailingPE": 14.89929,
    "momentum_2m": 0.036623610242749294,
    "momentum_1w": 0.02519155589137778,
    "FundamentalFilterRating": 83,
    "price": 62.90999984741211,
    "RSI (14)": 36.3,
    "EMA (20)": 62.88,
    "MACD (12,26,9)": -0.3732,
    "MACD_Signal (12,26,9)": -0.5244,
    "percent_change": -1.16,
    "TechFilterRating": 100.0,
    "news_sentiment_percent": 75.0,
    "social_sentiment_percent": null,
    "sector": "Financial Services",
    "sector_name": "XLF",
    "market_change_1d": 0.02460524140346365,
    "market_change_5d": 2.2758938082666047,
    "market_change_20d": 5.3534266348988835,
    "market_trend": "up",
    "sector_change_1d": -0.8003801601599081,
    "sector_change_5d": 0.6555829925114054,
    "sector_change_20d": -0.8003801601599081,
    "sector_trend": "neutral",
    "OverallRating": 86.0,
    "AITicker": "Citizens Financial Group, a financial services provider, primarily offers banking services.",
    "AIComment": "Citizens Financial Group (CFG) shows a neutral short-term trading outlook. The overall market is trending up, which is positive, but the financial sector remains neutral, potentially limiting CFG's momentum. The stock's recent performance and technical indicators like a negative MACD divergence suggest caution, making it a less favorable choice for a 2-10 day trading period.",
    "AIScore": 45,
    "SL": 61.62,
    "TP": 65.43,
    "SL10": 9.8,
    "TP10": 10.4,
    "Normalize": 7.9
  }
]